{"gamePk": 823801, "date": "2026-04-16", "awayTeam": "Toronto Blue Jays", "homeTeam": "Milwaukee Brewers", "awayAbbr": "TOR", "homeAbbr": "MIL", "venue": "American Family Field", "pitches": [{"pitcher": "Brandon Sproat", "pitcherId": 687075, "batter": "Davis Schneider", "batterId": 676914, "pitchType": "Four-Seam Fastball", "call": "Ball", "outcome": "ball", "pX": 0.733, "pZ": 3.3989, "szTop": 3.045, "szBottom": 1.537, "startSpeed": 98.6, "spinRate": 2042, "playId": "74258f81-7519-378c-a997-59753797ad26", "inning": 1, "halfInning": "top", "atBatIndex": 0, "pitchInPa": 1, "paResult": "Flyout"}, {"pitcher": "Brandon Sproat", "pitcherId": 687075, "batter": "Davis Schneider", "batterId": 676914, "pitchType": "Sinker", "call": "Called Strike", "outcome": "strike", "pX": -0.6982, "pZ": 2.9142, "szTop": 3.045, "szBottom": 1.537, "startSpeed": 96.8, "spinRate": 1996, "playId": "9f587a8e-c913-36bd-a8ea-f96b217456e8", "inning": 1, "halfInning": "top", "atBatIndex": 0, "pitchInPa": 2, "paResult": "Flyout"}, {"pitcher": "Brandon Sproat", "pitcherId": 687075, "batter": "Davis Schneider", "batterId": 676914, "pitchType": "Cutter", "call": "Swinging Strike", "outcome": "strike", "pX": -0.183, "pZ": 2.5192, "szTop": 3.045, "szBottom": 1.537, "startSpeed": 96.4, "spinRate": 2208, "playId": "c39b023e-a981-3542-8106-248493473c93", "inning": 1, "halfInning": "top", "atBatIndex": 0, "pitchInPa": 3, "paResult": "Flyout"}, {"pitcher": "Brandon Sproat", "pitcherId": 687075, "batter": "Davis Schneider", "batterId": 676914, "pitchType": "Sweeper", "call": "Ball", "outcome": "ball", "pX": -0.1804, "pZ": 1.0917, "szTop": 3.045, "szBottom": 1.537, "startSpeed": 88.3, "spinRate": 2522, "playId": "02f84b6a-57ea-32da-8e51-e3dce9f91b65", "inning": 1, "halfInning": "top", "atBatIndex": 0, "pitchInPa": 4, "paResult": "Flyout"}, {"pitcher": "Brandon Sproat", "pitcherId": 687075, "batter": "Davis Schneider", "batterId": 676914, "pitchType": "Sweeper", "call": "Ball", "outcome": "ball", "pX": -0.6997, "pZ": 3.0165, "szTop": 3.045, "szBottom": 1.537, "startSpeed": 87.0, "spinRate": 2526, "playId": "851928ca-6ec6-3ed8-a8f5-9f765b174ee6", "inning": 1, "halfInning": "top", "atBatIndex": 0, "pitchInPa": 5, "paResult": "Flyout"}, {"pitcher": "Brandon Sproat", "pitcherId": 687075, "batter": "Davis Schneider", "batterId": 676914, "pitchType": "Cutter", "call": "In play, out(s)", "outcome": "inplay", "pX": 0.3644, "pZ": 2.3438, "szTop": 3.045, "szBottom": 1.537, "startSpeed": 96.5, "spinRate": 2151, "playId": "776cd2af-4791-36ac-9aae-71c7164c3adb", "inning": 1, "halfInning": "top", "atBatIndex": 0, "pitchInPa": 6, "paResult": "Flyout", "launchSpeed": 94.8, "launchAngle": 61.0, "trajectory": "fly_ball"}, {"pitcher": "Brandon Sproat", "pitcherId": 687075, "batter": "Daulton Varsho", "batterId": 662139, "pitchType": "Four-Seam Fastball", "call": "Called Strike", "outcome": "strike", "pX": -0.5126, "pZ": 2.6276, "szTop": 3.037, "szBottom": 1.532, "startSpeed": 98.1, "spinRate": 2189, "playId": "5337299f-b163-350a-be85-059727a1e9ce", "inning": 1, "halfInning": "top", "atBatIndex": 1, "pitchInPa": 1, "paResult": "Strikeout"}, {"pitcher": "Brandon Sproat", "pitcherId": 687075, "batter": "Daulton Varsho", "batterId": 662139, "pitchType": "Cutter", "call": "Foul", "outcome": "strike", "pX": -0.5641, "pZ": 3.3062, "szTop": 3.037, "szBottom": 1.532, "startSpeed": 94.8, "spinRate": 2309, "playId": "45e64bad-51b5-357d-ba1f-980fca6bd3cf", "inning": 1, "halfInning": "top", "atBatIndex": 1, "pitchInPa": 2, "paResult": "Strikeout"}, {"pitcher": "Brandon Sproat", "pitcherId": 687075, "batter": "Daulton Varsho", "batterId": 662139, "pitchType": "Curveball", "call": "Foul Tip", "outcome": "strike", "pX": 0.4307, "pZ": 0.8933, "szTop": 3.037, "szBottom": 1.532, "startSpeed": 83.8, "spinRate": 2567, "playId": "f1adfda5-099b-3d19-9f69-fd90bb25fb83", "inning": 1, "halfInning": "top", "atBatIndex": 1, "pitchInPa": 3, "paResult": "Strikeout"}, {"pitcher": "Brandon Sproat", "pitcherId": 687075, "batter": "Vladimir Guerrero Jr.", "batterId": 665489, "pitchType": "Sinker", "call": "Ball", "outcome": "ball", "pX": 0.4748, "pZ": 1.4072, "szTop": 3.209, "szBottom": 1.619, "startSpeed": 98.0, "spinRate": 2064, "playId": "b7750529-ff28-390a-adf6-2e0505feb82e", "inning": 1, "halfInning": "top", "atBatIndex": 2, "pitchInPa": 1, "paResult": "Strikeout"}, {"pitcher": "Brandon Sproat", "pitcherId": 687075, "batter": "Vladimir Guerrero Jr.", "batterId": 665489, "pitchType": "Cutter", "call": "Called Strike", "outcome": "strike", "pX": -0.3889, "pZ": 1.8306, "szTop": 3.209, "szBottom": 1.619, "startSpeed": 95.5, "spinRate": 2133, "playId": "2d0a6449-836a-3992-93b9-4452641b0d4f", "inning": 1, "halfInning": "top", "atBatIndex": 2, "pitchInPa": 2, "paResult": "Strikeout"}, {"pitcher": "Brandon Sproat", "pitcherId": 687075, "batter": "Vladimir Guerrero Jr.", "batterId": 665489, "pitchType": "Cutter", "call": "Ball", "outcome": "ball", "pX": 1.3877, "pZ": 3.5521, "szTop": 3.209, "szBottom": 1.619, "startSpeed": 94.4, "spinRate": 2074, "playId": "6fa4abf8-6238-3602-ac3a-2100b43613c7", "inning": 1, "halfInning": "top", "atBatIndex": 2, "pitchInPa": 3, "paResult": "Strikeout"}, {"pitcher": "Brandon Sproat", "pitcherId": 687075, "batter": "Vladimir Guerrero Jr.", "batterId": 665489, "pitchType": "Sinker", "call": "Called Strike", "outcome": "strike", "pX": -0.3181, "pZ": 1.6984, "szTop": 3.209, "szBottom": 1.619, "startSpeed": 98.4, "spinRate": 2040, "playId": "be0b79e6-7bf6-353c-a6f6-bae44451aea5", "inning": 1, "halfInning": "top", "atBatIndex": 2, "pitchInPa": 4, "paResult": "Strikeout"}, {"pitcher": "Brandon Sproat", "pitcherId": 687075, "batter": "Vladimir Guerrero Jr.", "batterId": 665489, "pitchType": "Sweeper", "call": "Swinging Strike", "outcome": "strike", "pX": 0.6637, "pZ": 1.3875, "szTop": 3.209, "szBottom": 1.619, "startSpeed": 87.9, "spinRate": 2513, "playId": "22c1ca6b-1914-37ec-9a88-f062bb00aa8e", "inning": 1, "halfInning": "top", "atBatIndex": 2, "pitchInPa": 5, "paResult": "Strikeout"}, {"pitcher": "Patrick Corbin", "pitcherId": 571578, "batter": "Brandon Lockridge", "batterId": 663604, "pitchType": "Sinker", "call": "Called Strike", "outcome": "strike", "pX": 0.3395, "pZ": 3.1133, "szTop": 3.226, "szBottom": 1.628, "startSpeed": 91.1, "spinRate": 2108, "playId": "d5a1fbfa-542f-3f86-bef8-84e8329d543e", "inning": 1, "halfInning": "bottom", "atBatIndex": 3, "pitchInPa": 1, "paResult": "Groundout"}, {"pitcher": "Patrick Corbin", "pitcherId": 571578, "batter": "Brandon Lockridge", "batterId": 663604, "pitchType": "Sinker", "call": "Ball", "outcome": "ball", "pX": 1.5773, "pZ": 2.2148, "szTop": 3.226, "szBottom": 1.628, "startSpeed": 91.2, "spinRate": 2050, "playId": "734562b2-263a-3e29-9b1d-4af87c8e2b8a", "inning": 1, "halfInning": "bottom", "atBatIndex": 3, "pitchInPa": 2, "paResult": "Groundout"}, {"pitcher": "Patrick Corbin", "pitcherId": 571578, "batter": "Brandon Lockridge", "batterId": 663604, "pitchType": "Cutter", "call": "In play, out(s)", "outcome": "inplay", "pX": 0.1066, "pZ": 1.9579, "szTop": 3.226, "szBottom": 1.628, "startSpeed": 85.9, "spinRate": 2227, "playId": "ab2a5f52-0bb3-3889-96ce-79541c46cd55", "inning": 1, "halfInning": "bottom", "atBatIndex": 3, "pitchInPa": 3, "paResult": "Groundout", "launchSpeed": 106.6, "launchAngle": -5.0, "trajectory": "ground_ball"}, {"pitcher": "Patrick Corbin", "pitcherId": 571578, "batter": "Brice Turang", "batterId": 668930, "pitchType": "Four-Seam Fastball", "call": "Foul", "outcome": "strike", "pX": -0.0949, "pZ": 2.7845, "szTop": 3.21, "szBottom": 1.62, "startSpeed": 91.7, "spinRate": 2126, "playId": "1ab453bb-66b1-3339-977a-dee7de24d966", "inning": 1, "halfInning": "bottom", "atBatIndex": 4, "pitchInPa": 1, "paResult": "Strikeout"}, {"pitcher": "Patrick Corbin", "pitcherId": 571578, "batter": "Brice Turang", "batterId": 668930, "pitchType": "Slider", "call": "Ball", "outcome": "ball", "pX": -1.4026, "pZ": 0.621, "szTop": 3.21, "szBottom": 1.62, "startSpeed": 80.7, "spinRate": 2204, "playId": "050e754a-0d50-334e-b8da-29c153b8868f", "inning": 1, "halfInning": "bottom", "atBatIndex": 4, "pitchInPa": 2, "paResult": "Strikeout"}, {"pitcher": "Patrick Corbin", "pitcherId": 571578, "batter": "Brice Turang", "batterId": 668930, "pitchType": "Four-Seam Fastball", "call": "Ball", "outcome": "ball", "pX": -0.6321, "pZ": 3.48, "szTop": 3.21, "szBottom": 1.62, "startSpeed": 91.4, "spinRate": 2030, "playId": "842aa898-ed35-3e2f-9f4d-b12f1b0abee7", "inning": 1, "halfInning": "bottom", "atBatIndex": 4, "pitchInPa": 3, "paResult": "Strikeout"}, {"pitcher": "Patrick Corbin", "pitcherId": 571578, "batter": "Brice Turang", "batterId": 668930, "pitchType": "Four-Seam Fastball", "call": "Ball", "outcome": "ball", "pX": -0.9739, "pZ": 2.8728, "szTop": 3.21, "szBottom": 1.62, "startSpeed": 91.8, "spinRate": 2022, "playId": "06b8abd3-d914-3ca4-b808-b3cfb0e57814", "inning": 1, "halfInning": "bottom", "atBatIndex": 4, "pitchInPa": 4, "paResult": "Strikeout"}, {"pitcher": "Patrick Corbin", "pitcherId": 571578, "batter": "Brice Turang", "batterId": 668930, "pitchType": "Four-Seam Fastball", "call": "Called Strike", "outcome": "strike", "pX": 0.5921, "pZ": 2.3892, "szTop": 3.21, "szBottom": 1.62, "startSpeed": 90.9, "spinRate": 2041, "playId": "e9ffbb53-3b37-325d-95e8-6a8f3e26bec9", "inning": 1, "halfInning": "bottom", "atBatIndex": 4, "pitchInPa": 5, "paResult": "Strikeout"}, {"pitcher": "Patrick Corbin", "pitcherId": 571578, "batter": "Brice Turang", "batterId": 668930, "pitchType": "Four-Seam Fastball", "call": "Foul", "outcome": "strike", "pX": 0.3081, "pZ": 2.7968, "szTop": 3.21, "szBottom": 1.62, "startSpeed": 91.4, "spinRate": 2014, "playId": "8cbcebdb-e0ae-3982-870b-fcaf0441ca83", "inning": 1, "halfInning": "bottom", "atBatIndex": 4, "pitchInPa": 6, "paResult": "Strikeout"}, {"pitcher": "Patrick Corbin", "pitcherId": 571578, "batter": "Brice Turang", "batterId": 668930, "pitchType": "Slider", "call": "Swinging Strike", "outcome": "strike", "pX": -0.154, "pZ": 1.8154, "szTop": 3.21, "szBottom": 1.62, "startSpeed": 81.2, "spinRate": 2139, "playId": "8f4b78ba-ecff-3fd9-98ea-fa8297956519", "inning": 1, "halfInning": "bottom", "atBatIndex": 4, "pitchInPa": 7, "paResult": "Strikeout"}, {"pitcher": "Patrick Corbin", "pitcherId": 571578, "batter": "William Contreras", "batterId": 661388, "pitchType": "Sinker", "call": "Ball", "outcome": "ball", "pX": 0.4297, "pZ": 1.1058, "szTop": 3.133, "szBottom": 1.581, "startSpeed": 91.3, "spinRate": 2069, "playId": "169addf4-0103-3a49-b886-31aa8d0e168b", "inning": 1, "halfInning": "bottom", "atBatIndex": 5, "pitchInPa": 1, "paResult": "Groundout"}, {"pitcher": "Patrick Corbin", "pitcherId": 571578, "batter": "William Contreras", "batterId": 661388, "pitchType": "Sinker", "call": "In play, out(s)", "outcome": "inplay", "pX": 0.1416, "pZ": 1.737, "szTop": 3.133, "szBottom": 1.581, "startSpeed": 92.1, "spinRate": 2091, "playId": "17b4cb02-f13c-32a5-b222-7045ee0d6605", "inning": 1, "halfInning": "bottom", "atBatIndex": 5, "pitchInPa": 2, "paResult": "Groundout", "launchSpeed": 89.5, "launchAngle": -10.0, "trajectory": "ground_ball"}, {"pitcher": "Brandon Sproat", "pitcherId": 687075, "batter": "Jes\u00fas S\u00e1nchez", "batterId": 660821, "pitchType": "Four-Seam Fastball", "call": "Foul", "outcome": "strike", "pX": 0.592, "pZ": 2.9128, "szTop": 3.335, "szBottom": 1.683, "startSpeed": 97.1, "spinRate": 2146, "playId": "404cd100-a89f-3a5e-a635-50681e83090b", "inning": 2, "halfInning": "top", "atBatIndex": 6, "pitchInPa": 1, "paResult": "Groundout"}, {"pitcher": "Brandon Sproat", "pitcherId": 687075, "batter": "Jes\u00fas S\u00e1nchez", "batterId": 660821, "pitchType": "Cutter", "call": "In play, out(s)", "outcome": "inplay", "pX": -0.3188, "pZ": 2.0802, "szTop": 3.335, "szBottom": 1.683, "startSpeed": 95.5, "spinRate": 2146, "playId": "464ca0ef-785c-30c0-9c93-e6f4b2f6fa37", "inning": 2, "halfInning": "top", "atBatIndex": 6, "pitchInPa": 2, "paResult": "Groundout", "launchSpeed": 100.1, "launchAngle": -21.0, "trajectory": "ground_ball"}, {"pitcher": "Brandon Sproat", "pitcherId": 687075, "batter": "Lenyn Sosa", "batterId": 672820, "pitchType": "Sinker", "call": "In play, out(s)", "outcome": "inplay", "pX": -1.0109, "pZ": 3.5857, "szTop": 3.153, "szBottom": 1.591, "startSpeed": 96.7, "spinRate": 1932, "playId": "bf3cf4bf-a4cd-3063-863a-f8368cb88785", "inning": 2, "halfInning": "top", "atBatIndex": 7, "pitchInPa": 1, "paResult": "Pop Out", "launchSpeed": 53.0, "launchAngle": 72.0, "trajectory": "popup"}, {"pitcher": "Brandon Sproat", "pitcherId": 687075, "batter": "Kazuma Okamoto", "batterId": 672960, "pitchType": "Sinker", "call": "Foul", "outcome": "strike", "pX": -0.3086, "pZ": 2.3302, "szTop": 3.256, "szBottom": 1.643, "startSpeed": 96.9, "spinRate": 2014, "playId": "7eeb436e-958a-3ed2-9be8-2f14cd3f127c", "inning": 2, "halfInning": "top", "atBatIndex": 8, "pitchInPa": 1, "paResult": "Flyout"}, {"pitcher": "Brandon Sproat", "pitcherId": 687075, "batter": "Kazuma Okamoto", "batterId": 672960, "pitchType": "Cutter", "call": "Foul", "outcome": "strike", "pX": -0.0632, "pZ": 2.3096, "szTop": 3.256, "szBottom": 1.643, "startSpeed": 95.0, "spinRate": 2110, "playId": "34036f1e-544d-3e7b-9432-2a0506abe930", "inning": 2, "halfInning": "top", "atBatIndex": 8, "pitchInPa": 2, "paResult": "Flyout"}, {"pitcher": "Brandon Sproat", "pitcherId": 687075, "batter": "Kazuma Okamoto", "batterId": 672960, "pitchType": "Sweeper", "call": "In play, out(s)", "outcome": "inplay", "pX": -0.0903, "pZ": 2.2425, "szTop": 3.256, "szBottom": 1.643, "startSpeed": 87.5, "spinRate": 2339, "playId": "ce49c636-b992-34dc-a515-d58a76dd3a72", "inning": 2, "halfInning": "top", "atBatIndex": 8, "pitchInPa": 3, "paResult": "Flyout", "launchSpeed": 96.9, "launchAngle": 30.0, "trajectory": "fly_ball"}, {"pitcher": "Patrick Corbin", "pitcherId": 571578, "batter": "Gary S\u00e1nchez", "batterId": 596142, "pitchType": "Sinker", "call": "Called Strike", "outcome": "strike", "pX": 0.8894, "pZ": 2.5087, "szTop": 3.311, "szBottom": 1.671, "startSpeed": 91.4, "spinRate": 2136, "playId": "06860239-9d48-3f7c-bf37-2a2c705d20b3", "inning": 2, "halfInning": "bottom", "atBatIndex": 9, "pitchInPa": 1, "paResult": "Single"}, {"pitcher": "Patrick Corbin", "pitcherId": 571578, "batter": "Gary S\u00e1nchez", "batterId": 596142, "pitchType": "Cutter", "call": "Ball", "outcome": "ball", "pX": -0.7527, "pZ": 3.4866, "szTop": 3.311, "szBottom": 1.671, "startSpeed": 87.3, "spinRate": 2329, "playId": "3e21388e-75ba-34c3-9a6a-b4d4d0288f35", "inning": 2, "halfInning": "bottom", "atBatIndex": 9, "pitchInPa": 2, "paResult": "Single"}, {"pitcher": "Patrick Corbin", "pitcherId": 571578, "batter": "Gary S\u00e1nchez", "batterId": 596142, "pitchType": "Sinker", "call": "Ball", "outcome": "ball", "pX": 0.9269, "pZ": 1.7669, "szTop": 3.311, "szBottom": 1.671, "startSpeed": 91.8, "spinRate": 2086, "playId": "19c06b8a-c052-31e7-acf4-c45fa40898ba", "inning": 2, "halfInning": "bottom", "atBatIndex": 9, "pitchInPa": 3, "paResult": "Single"}, {"pitcher": "Patrick Corbin", "pitcherId": 571578, "batter": "Gary S\u00e1nchez", "batterId": 596142, "pitchType": "Sinker", "call": "Called Strike", "outcome": "strike", "pX": -0.0439, "pZ": 2.1255, "szTop": 3.311, "szBottom": 1.671, "startSpeed": 92.6, "spinRate": 2163, "playId": "3f0a5f82-579a-3f2c-9341-6a0bb5562859", "inning": 2, "halfInning": "bottom", "atBatIndex": 9, "pitchInPa": 4, "paResult": "Single"}, {"pitcher": "Patrick Corbin", "pitcherId": 571578, "batter": "Gary S\u00e1nchez", "batterId": 596142, "pitchType": "Four-Seam Fastball", "call": "Foul", "outcome": "strike", "pX": -0.0513, "pZ": 2.5965, "szTop": 3.311, "szBottom": 1.671, "startSpeed": 92.7, "spinRate": 2170, "playId": "67b6b2ee-f1c3-3e24-82f6-e5602d81c76a", "inning": 2, "halfInning": "bottom", "atBatIndex": 9, "pitchInPa": 5, "paResult": "Single"}, {"pitcher": "Patrick Corbin", "pitcherId": 571578, "batter": "Gary S\u00e1nchez", "batterId": 596142, "pitchType": "Slider", "call": "Ball", "outcome": "ball", "pX": 0.1819, "pZ": 0.9538, "szTop": 3.311, "szBottom": 1.671, "startSpeed": 82.1, "spinRate": 2371, "playId": "b5716755-da1f-38e3-8dfe-9b9d4fdbff6a", "inning": 2, "halfInning": "bottom", "atBatIndex": 9, "pitchInPa": 6, "paResult": "Single"}, {"pitcher": "Patrick Corbin", "pitcherId": 571578, "batter": "Gary S\u00e1nchez", "batterId": 596142, "pitchType": "Sinker", "call": "In play, no out", "outcome": "inplay", "pX": 0.4168, "pZ": 2.6094, "szTop": 3.311, "szBottom": 1.671, "startSpeed": 91.8, "spinRate": 1884, "playId": "8def7d44-b0c2-3f23-8ba4-623ba3428466", "inning": 2, "halfInning": "bottom", "atBatIndex": 9, "pitchInPa": 7, "paResult": "Single", "launchSpeed": 108.8, "launchAngle": 11.0, "trajectory": "line_drive"}, {"pitcher": "Patrick Corbin", "pitcherId": 571578, "batter": "Luis Rengifo", "batterId": 650859, "pitchType": "Cutter", "call": "Ball", "outcome": "ball", "pX": 1.3002, "pZ": 2.4319, "szTop": 3.087, "szBottom": 1.558, "startSpeed": 86.4, "spinRate": 2258, "playId": "cd760609-c85f-3bc2-a471-5a41c2120308", "inning": 2, "halfInning": "bottom", "atBatIndex": 10, "pitchInPa": 1, "paResult": "Flyout"}, {"pitcher": "Patrick Corbin", "pitcherId": 571578, "batter": "Luis Rengifo", "batterId": 650859, "pitchType": "Cutter", "call": "In play, out(s)", "outcome": "inplay", "pX": -0.512, "pZ": 1.6574, "szTop": 3.087, "szBottom": 1.558, "startSpeed": 86.5, "spinRate": 2320, "playId": "f72b74f7-993b-34a8-a628-7068536c4633", "inning": 2, "halfInning": "bottom", "atBatIndex": 10, "pitchInPa": 2, "paResult": "Flyout", "launchSpeed": 103.5, "launchAngle": 44.0, "trajectory": "fly_ball"}, {"pitcher": "Patrick Corbin", "pitcherId": 571578, "batter": "Luis Matos", "batterId": 682641, "pitchType": "Slider", "call": "Swinging Strike", "outcome": "strike", "pX": 0.5216, "pZ": 0.9479, "szTop": 3.168, "szBottom": 1.599, "startSpeed": 76.0, "spinRate": 2074, "playId": "a83ebbd2-c835-3061-8100-2c5a887b38cd", "inning": 2, "halfInning": "bottom", "atBatIndex": 11, "pitchInPa": 1, "paResult": "Pop Out"}, {"pitcher": "Patrick Corbin", "pitcherId": 571578, "batter": "Luis Matos", "batterId": 682641, "pitchType": "Slider", "call": "Ball", "outcome": "ball", "pX": 1.0073, "pZ": 1.8801, "szTop": 3.168, "szBottom": 1.599, "startSpeed": 80.0, "spinRate": 2248, "playId": "775688d3-8f53-3600-88dc-83227c00c98c", "inning": 2, "halfInning": "bottom", "atBatIndex": 11, "pitchInPa": 2, "paResult": "Pop Out"}, {"pitcher": "Patrick Corbin", "pitcherId": 571578, "batter": "Luis Matos", "batterId": 682641, "pitchType": "Four-Seam Fastball", "call": "Foul", "outcome": "strike", "pX": 0.2151, "pZ": 2.3965, "szTop": 3.168, "szBottom": 1.599, "startSpeed": 90.7, "spinRate": 2009, "playId": "c625210e-dcca-36f6-8c25-c05bf18a4f5c", "inning": 2, "halfInning": "bottom", "atBatIndex": 11, "pitchInPa": 3, "paResult": "Pop Out"}, {"pitcher": "Patrick Corbin", "pitcherId": 571578, "batter": "Luis Matos", "batterId": 682641, "pitchType": "Slider", "call": "In play, out(s)", "outcome": "inplay", "pX": -0.313, "pZ": 1.4053, "szTop": 3.168, "szBottom": 1.599, "startSpeed": 81.7, "spinRate": 2295, "playId": "c2ccc151-4b4b-37ad-90ba-149df06e8df0", "inning": 2, "halfInning": "bottom", "atBatIndex": 11, "pitchInPa": 4, "paResult": "Pop Out", "launchSpeed": 86.7, "launchAngle": 63.0, "trajectory": "popup"}, {"pitcher": "Patrick Corbin", "pitcherId": 571578, "batter": "Greg Jones", "batterId": 675659, "pitchType": "Sinker", "call": "In play, out(s)", "outcome": "inplay", "pX": 0.3318, "pZ": 2.3405, "szTop": 3.203, "szBottom": 1.617, "startSpeed": 91.4, "spinRate": 2110, "playId": "f69bd5a1-2613-32ec-83b8-e0b7c128b6e3", "inning": 2, "halfInning": "bottom", "atBatIndex": 12, "pitchInPa": 1, "paResult": "Groundout", "launchSpeed": 57.1, "launchAngle": -34.0, "trajectory": "ground_ball"}, {"pitcher": "Brandon Sproat", "pitcherId": 687075, "batter": "Andr\u00e9s Gim\u00e9nez", "batterId": 665926, "pitchType": "Cutter", "call": "Ball", "outcome": "ball", "pX": 1.3178, "pZ": 1.3695, "szTop": 3.165, "szBottom": 1.597, "startSpeed": 92.3, "spinRate": 1996, "playId": "831f52c5-0d4a-3bd1-871f-33a06dd95649", "inning": 3, "halfInning": "top", "atBatIndex": 13, "pitchInPa": 1, "paResult": "Double"}, {"pitcher": "Brandon Sproat", "pitcherId": 687075, "batter": "Andr\u00e9s Gim\u00e9nez", "batterId": 665926, "pitchType": "Four-Seam Fastball", "call": "In play, no out", "outcome": "inplay", "pX": 0.4844, "pZ": 1.4728, "szTop": 3.165, "szBottom": 1.597, "startSpeed": 96.1, "spinRate": 1979, "playId": "4d858e82-9a58-32b5-b739-8707295dd1c5", "inning": 3, "halfInning": "top", "atBatIndex": 13, "pitchInPa": 2, "paResult": "Double", "launchSpeed": 91.9, "launchAngle": -15.0, "trajectory": "ground_ball"}, {"pitcher": "Brandon Sproat", "pitcherId": 687075, "batter": "Ernie Clement", "batterId": 676391, "pitchType": "Sinker", "call": "Ball", "outcome": "ball", "pX": -0.1889, "pZ": 4.3777, "szTop": 3.191, "szBottom": 1.61, "startSpeed": 95.1, "spinRate": 1960, "playId": "c4619ef3-f82d-3406-8f6e-ccab794d1795", "inning": 3, "halfInning": "top", "atBatIndex": 14, "pitchInPa": 1, "paResult": "Single"}, {"pitcher": "Brandon Sproat", "pitcherId": 687075, "batter": "Ernie Clement", "batterId": 676391, "pitchType": "Curveball", "call": "In play, no out", "outcome": "inplay", "pX": -0.3119, "pZ": 1.4971, "szTop": 3.191, "szBottom": 1.61, "startSpeed": 81.1, "spinRate": 2502, "playId": "df5eda87-bcbd-3cd6-816c-349d2fbe10d0", "inning": 3, "halfInning": "top", "atBatIndex": 14, "pitchInPa": 2, "paResult": "Single", "launchSpeed": 102.0, "launchAngle": 12.0, "trajectory": "line_drive"}, {"pitcher": "Brandon Sproat", "pitcherId": 687075, "batter": "Tyler Heineman", "batterId": 623168, "pitchType": "Cutter", "call": "Ball", "outcome": "ball", "pX": -0.4691, "pZ": 4.7483, "szTop": 3.11, "szBottom": 1.57, "startSpeed": 92.8, "spinRate": 2009, "playId": "57c2212a-06dd-3790-8fa8-dcbdb5ea5618", "inning": 3, "halfInning": "top", "atBatIndex": 15, "pitchInPa": 1, "paResult": "Sac Bunt"}, {"pitcher": "Brandon Sproat", "pitcherId": 687075, "batter": "Tyler Heineman", "batterId": 623168, "pitchType": "Cutter", "call": "In play, run(s)", "outcome": "inplay", "pX": 0.0053, "pZ": 2.994, "szTop": 3.11, "szBottom": 1.57, "startSpeed": 93.6, "spinRate": 2027, "playId": "f1bf709a-2f0f-30dd-98bd-0ceef8205584", "inning": 3, "halfInning": "top", "atBatIndex": 15, "pitchInPa": 2, "paResult": "Sac Bunt", "launchSpeed": 36.5, "launchAngle": -40.0, "trajectory": "bunt_grounder"}, {"pitcher": "Brandon Sproat", "pitcherId": 687075, "batter": "Davis Schneider", "batterId": 676914, "pitchType": "Cutter", "call": "Called Strike", "outcome": "strike", "pX": 0.5074, "pZ": 2.7556, "szTop": 3.045, "szBottom": 1.537, "startSpeed": 93.9, "spinRate": 2215, "playId": "575ff265-94d8-3bbc-b948-4128959f9899", "inning": 3, "halfInning": "top", "atBatIndex": 16, "pitchInPa": 1, "paResult": "Flyout"}, {"pitcher": "Brandon Sproat", "pitcherId": 687075, "batter": "Davis Schneider", "batterId": 676914, "pitchType": "Sweeper", "call": "In play, out(s)", "outcome": "inplay", "pX": 0.6758, "pZ": 2.185, "szTop": 3.045, "szBottom": 1.537, "startSpeed": 87.9, "spinRate": 2364, "playId": "c6e6cfdb-bea4-3efc-917d-d181187ba82f", "inning": 3, "halfInning": "top", "atBatIndex": 16, "pitchInPa": 2, "paResult": "Flyout", "launchSpeed": 87.0, "launchAngle": 36.0, "trajectory": "fly_ball"}, {"pitcher": "Brandon Sproat", "pitcherId": 687075, "batter": "Daulton Varsho", "batterId": 662139, "pitchType": "Curveball", "call": "Ball", "outcome": "ball", "pX": -0.4747, "pZ": 1.0136, "szTop": 3.037, "szBottom": 1.532, "startSpeed": 83.1, "spinRate": 2628, "playId": "1edcfd11-99a0-3c75-825b-735fd7da59a6", "inning": 3, "halfInning": "top", "atBatIndex": 17, "pitchInPa": 1, "paResult": "Flyout"}, {"pitcher": "Brandon Sproat", "pitcherId": 687075, "batter": "Daulton Varsho", "batterId": 662139, "pitchType": "Cutter", "call": "Ball", "outcome": "ball", "pX": 1.7073, "pZ": 2.3818, "szTop": 3.037, "szBottom": 1.532, "startSpeed": 93.4, "spinRate": 2136, "playId": "f5233a2d-acf2-3de9-b595-b55dee098e8c", "inning": 3, "halfInning": "top", "atBatIndex": 17, "pitchInPa": 2, "paResult": "Flyout"}, {"pitcher": "Brandon Sproat", "pitcherId": 687075, "batter": "Daulton Varsho", "batterId": 662139, "pitchType": "Cutter", "call": "In play, out(s)", "outcome": "inplay", "pX": 0.4222, "pZ": 2.3036, "szTop": 3.037, "szBottom": 1.532, "startSpeed": 93.7, "spinRate": 2139, "playId": "99a083ed-dd13-3a34-ba3c-103932c0da65", "inning": 3, "halfInning": "top", "atBatIndex": 17, "pitchInPa": 3, "paResult": "Flyout", "launchSpeed": 82.8, "launchAngle": 54.0, "trajectory": "fly_ball"}, {"pitcher": "Patrick Corbin", "pitcherId": 571578, "batter": "David Hamilton", "batterId": 666152, "pitchType": "Four-Seam Fastball", "call": "Called Strike", "outcome": "strike", "pX": 0.0114, "pZ": 2.8847, "szTop": 3.135, "szBottom": 1.582, "startSpeed": 90.0, "spinRate": 2149, "playId": "05edd98f-4e50-3b23-b409-13cd5c9ad46b", "inning": 3, "halfInning": "bottom", "atBatIndex": 18, "pitchInPa": 1, "paResult": "Strikeout"}, {"pitcher": "Patrick Corbin", "pitcherId": 571578, "batter": "David Hamilton", "batterId": 666152, "pitchType": "Sinker", "call": "Foul", "outcome": "strike", "pX": 0.4002, "pZ": 2.4431, "szTop": 3.135, "szBottom": 1.582, "startSpeed": 91.2, "spinRate": 2027, "playId": "1998a75a-2649-3f32-be2c-4a5867b64af3", "inning": 3, "halfInning": "bottom", "atBatIndex": 18, "pitchInPa": 2, "paResult": "Strikeout"}, {"pitcher": "Patrick Corbin", "pitcherId": 571578, "batter": "David Hamilton", "batterId": 666152, "pitchType": "Sinker", "call": "Ball", "outcome": "ball", "pX": -1.4705, "pZ": 2.1905, "szTop": 3.135, "szBottom": 1.582, "startSpeed": 91.8, "spinRate": 2062, "playId": "e465a961-464f-3734-a702-61813f67ae1f", "inning": 3, "halfInning": "bottom", "atBatIndex": 18, "pitchInPa": 3, "paResult": "Strikeout"}, {"pitcher": "Patrick Corbin", "pitcherId": 571578, "batter": "David Hamilton", "batterId": 666152, "pitchType": "Slider", "call": "Swinging Strike (Blocked)", "outcome": "strike", "pX": -0.6779, "pZ": 0.7029, "szTop": 3.135, "szBottom": 1.582, "startSpeed": 79.6, "spinRate": 2331, "playId": "07757144-ef97-33ae-87cb-c11a9f7b81b1", "inning": 3, "halfInning": "bottom", "atBatIndex": 18, "pitchInPa": 4, "paResult": "Strikeout"}, {"pitcher": "Patrick Corbin", "pitcherId": 571578, "batter": "Joey Ortiz", "batterId": 687401, "pitchType": "Cutter", "call": "Ball", "outcome": "ball", "pX": -1.3214, "pZ": 1.0846, "szTop": 3.137, "szBottom": 1.583, "startSpeed": 85.9, "spinRate": 2257, "playId": "6e18484e-28a1-3a04-aa42-066cee814d2a", "inning": 3, "halfInning": "bottom", "atBatIndex": 19, "pitchInPa": 1, "paResult": "Walk"}, {"pitcher": "Patrick Corbin", "pitcherId": 571578, "batter": "Joey Ortiz", "batterId": 687401, "pitchType": "Sinker", "call": "Ball", "outcome": "ball", "pX": 0.7063, "pZ": 1.1565, "szTop": 3.137, "szBottom": 1.583, "startSpeed": 90.8, "spinRate": 1959, "playId": "8ab1771c-5f48-3f49-b1cf-533f1616ed22", "inning": 3, "halfInning": "bottom", "atBatIndex": 19, "pitchInPa": 2, "paResult": "Walk"}, {"pitcher": "Patrick Corbin", "pitcherId": 571578, "batter": "Joey Ortiz", "batterId": 687401, "pitchType": "Cutter", "call": "Ball", "outcome": "ball", "pX": 0.8371, "pZ": 3.3626, "szTop": 3.137, "szBottom": 1.583, "startSpeed": 84.6, "spinRate": 2258, "playId": "7cbe41d9-efac-378e-a86c-7adcac1ee2f1", "inning": 3, "halfInning": "bottom", "atBatIndex": 19, "pitchInPa": 3, "paResult": "Walk"}, {"pitcher": "Patrick Corbin", "pitcherId": 571578, "batter": "Joey Ortiz", "batterId": 687401, "pitchType": "Sinker", "call": "Called Strike", "outcome": "strike", "pX": -0.1344, "pZ": 2.5652, "szTop": 3.137, "szBottom": 1.583, "startSpeed": 89.4, "spinRate": 2023, "playId": "192831f5-38f3-3ddd-82dc-2bd34bf2ac67", "inning": 3, "halfInning": "bottom", "atBatIndex": 19, "pitchInPa": 4, "paResult": "Walk"}, {"pitcher": "Patrick Corbin", "pitcherId": 571578, "batter": "Joey Ortiz", "batterId": 687401, "pitchType": "Sinker", "call": "Ball", "outcome": "ball", "pX": 1.057, "pZ": 2.6037, "szTop": 3.137, "szBottom": 1.583, "startSpeed": 90.7, "spinRate": 1930, "playId": "4a65154d-0249-3e65-99f9-a7d64d317abb", "inning": 3, "halfInning": "bottom", "atBatIndex": 19, "pitchInPa": 5, "paResult": "Walk"}, {"pitcher": "Patrick Corbin", "pitcherId": 571578, "batter": "Brandon Lockridge", "batterId": 663604, "pitchType": "Cutter", "call": "Called Strike", "outcome": "strike", "pX": -0.4464, "pZ": 2.9915, "szTop": 3.226, "szBottom": 1.628, "startSpeed": 87.2, "spinRate": 2315, "playId": "01e2a005-b0ad-3ae8-b68e-9c267fdafabd", "inning": 3, "halfInning": "bottom", "atBatIndex": 20, "pitchInPa": 1, "paResult": "Strikeout"}, {"pitcher": "Patrick Corbin", "pitcherId": 571578, "batter": "Brandon Lockridge", "batterId": 663604, "pitchType": "Changeup", "call": "Swinging Strike", "outcome": "strike", "pX": 1.1229, "pZ": 3.0555, "szTop": 3.226, "szBottom": 1.628, "startSpeed": 78.7, "spinRate": 1291, "playId": "5268823d-3f77-35d5-a484-d2152458297c", "inning": 3, "halfInning": "bottom", "atBatIndex": 20, "pitchInPa": 2, "paResult": "Strikeout"}, {"pitcher": "Patrick Corbin", "pitcherId": 571578, "batter": "Brandon Lockridge", "batterId": 663604, "pitchType": "Four-Seam Fastball", "call": "Foul Tip", "outcome": "strike", "pX": 0.062, "pZ": 3.1754, "szTop": 3.226, "szBottom": 1.628, "startSpeed": 92.1, "spinRate": 2154, "playId": "447bfce1-6382-33b9-911c-c7381506e8c8", "inning": 3, "halfInning": "bottom", "atBatIndex": 20, "pitchInPa": 3, "paResult": "Strikeout"}, {"pitcher": "Patrick Corbin", "pitcherId": 571578, "batter": "Brice Turang", "batterId": 668930, "pitchType": "Cutter", "call": "Foul", "outcome": "strike", "pX": -0.1926, "pZ": 2.4404, "szTop": 3.21, "szBottom": 1.62, "startSpeed": 87.1, "spinRate": 2233, "playId": "8e42543f-33f9-3782-87e4-7dacc7c68869", "inning": 3, "halfInning": "bottom", "atBatIndex": 21, "pitchInPa": 1, "paResult": "Caught Stealing 2B"}, {"pitcher": "Patrick Corbin", "pitcherId": 571578, "batter": "Brice Turang", "batterId": 668930, "pitchType": "Slider", "call": "Ball", "outcome": "ball", "pX": -0.7918, "pZ": 1.5261, "szTop": 3.21, "szBottom": 1.62, "startSpeed": 79.6, "spinRate": 2192, "playId": "53f6c79f-7ba7-3bf5-ae21-26f207f89332", "inning": 3, "halfInning": "bottom", "atBatIndex": 21, "pitchInPa": 2, "paResult": "Caught Stealing 2B"}, {"pitcher": "Brandon Sproat", "pitcherId": 687075, "batter": "Vladimir Guerrero Jr.", "batterId": 665489, "pitchType": "Cutter", "call": "Ball", "outcome": "ball", "pX": 1.0381, "pZ": 2.1106, "szTop": 3.209, "szBottom": 1.619, "startSpeed": 93.0, "spinRate": 2036, "playId": "346d32ee-dc0b-31a7-84d1-90e94f866ae1", "inning": 4, "halfInning": "top", "atBatIndex": 22, "pitchInPa": 1, "paResult": "Strikeout"}, {"pitcher": "Brandon Sproat", "pitcherId": 687075, "batter": "Vladimir Guerrero Jr.", "batterId": 665489, "pitchType": "Cutter", "call": "Swinging Strike", "outcome": "strike", "pX": 0.4962, "pZ": 3.1849, "szTop": 3.209, "szBottom": 1.619, "startSpeed": 93.4, "spinRate": 2053, "playId": "81bf7792-5923-3d1f-86a2-a16fe9aa1f5f", "inning": 4, "halfInning": "top", "atBatIndex": 22, "pitchInPa": 2, "paResult": "Strikeout"}, {"pitcher": "Brandon Sproat", "pitcherId": 687075, "batter": "Vladimir Guerrero Jr.", "batterId": 665489, "pitchType": "Sweeper", "call": "Swinging Strike", "outcome": "strike", "pX": 0.6392, "pZ": 2.0307, "szTop": 3.209, "szBottom": 1.619, "startSpeed": 85.7, "spinRate": 2318, "playId": "5ce4b07d-7c5d-3ff4-b9e2-3423df4cdc5b", "inning": 4, "halfInning": "top", "atBatIndex": 22, "pitchInPa": 3, "paResult": "Strikeout"}, {"pitcher": "Brandon Sproat", "pitcherId": 687075, "batter": "Vladimir Guerrero Jr.", "batterId": 665489, "pitchType": "Sweeper", "call": "Swinging Strike", "outcome": "strike", "pX": 0.3012, "pZ": 2.319, "szTop": 3.209, "szBottom": 1.619, "startSpeed": 85.5, "spinRate": 2445, "playId": "198388e6-cd5d-3d7b-9141-f653e9586898", "inning": 4, "halfInning": "top", "atBatIndex": 22, "pitchInPa": 4, "paResult": "Strikeout"}, {"pitcher": "Brandon Sproat", "pitcherId": 687075, "batter": "Jes\u00fas S\u00e1nchez", "batterId": 660821, "pitchType": "Four-Seam Fastball", "call": "Foul", "outcome": "strike", "pX": 0.4371, "pZ": 2.1627, "szTop": 3.335, "szBottom": 1.683, "startSpeed": 96.5, "spinRate": 1977, "playId": "b079ce81-30f8-372e-9fbd-af20c24db55b", "inning": 4, "halfInning": "top", "atBatIndex": 23, "pitchInPa": 1, "paResult": "Groundout"}, {"pitcher": "Brandon Sproat", "pitcherId": 687075, "batter": "Jes\u00fas S\u00e1nchez", "batterId": 660821, "pitchType": "Sweeper", "call": "Ball", "outcome": "ball", "pX": -0.2296, "pZ": 0.3545, "szTop": 3.335, "szBottom": 1.683, "startSpeed": 85.4, "spinRate": 2270, "playId": "9ce8e7b0-a586-3896-83ba-1654634fcf88", "inning": 4, "halfInning": "top", "atBatIndex": 23, "pitchInPa": 2, "paResult": "Groundout"}, {"pitcher": "Brandon Sproat", "pitcherId": 687075, "batter": "Jes\u00fas S\u00e1nchez", "batterId": 660821, "pitchType": "Cutter", "call": "Foul", "outcome": "strike", "pX": 0.7343, "pZ": 2.3014, "szTop": 3.335, "szBottom": 1.683, "startSpeed": 93.0, "spinRate": 2171, "playId": "f033e367-0016-343a-843f-fb5869074d8a", "inning": 4, "halfInning": "top", "atBatIndex": 23, "pitchInPa": 3, "paResult": "Groundout"}, {"pitcher": "Brandon Sproat", "pitcherId": 687075, "batter": "Jes\u00fas S\u00e1nchez", "batterId": 660821, "pitchType": "Four-Seam Fastball", "call": "Foul", "outcome": "strike", "pX": -0.5498, "pZ": 2.5227, "szTop": 3.335, "szBottom": 1.683, "startSpeed": 96.8, "spinRate": 2033, "playId": "d70c0a4a-7180-3249-b008-8d7cd1454dee", "inning": 4, "halfInning": "top", "atBatIndex": 23, "pitchInPa": 4, "paResult": "Groundout"}, {"pitcher": "Brandon Sproat", "pitcherId": 687075, "batter": "Jes\u00fas S\u00e1nchez", "batterId": 660821, "pitchType": "Curveball", "call": "Foul", "outcome": "strike", "pX": -0.295, "pZ": 1.0175, "szTop": 3.335, "szBottom": 1.683, "startSpeed": 84.2, "spinRate": 2639, "playId": "713dc43a-afc7-3c0f-a3e9-96b2674ee198", "inning": 4, "halfInning": "top", "atBatIndex": 23, "pitchInPa": 5, "paResult": "Groundout"}, {"pitcher": "Brandon Sproat", "pitcherId": 687075, "batter": "Jes\u00fas S\u00e1nchez", "batterId": 660821, "pitchType": "Curveball", "call": "In play, out(s)", "outcome": "inplay", "pX": -0.6948, "pZ": 0.9893, "szTop": 3.335, "szBottom": 1.683, "startSpeed": 82.0, "spinRate": 2651, "playId": "b3ede9c6-4533-3614-8ad9-a54a4b96f067", "inning": 4, "halfInning": "top", "atBatIndex": 23, "pitchInPa": 6, "paResult": "Groundout", "launchSpeed": 76.1, "launchAngle": -31.0, "trajectory": "ground_ball"}, {"pitcher": "Brandon Sproat", "pitcherId": 687075, "batter": "Lenyn Sosa", "batterId": 672820, "pitchType": "Cutter", "call": "Called Strike", "outcome": "strike", "pX": 0.643, "pZ": 2.6224, "szTop": 3.153, "szBottom": 1.591, "startSpeed": 93.7, "spinRate": 2021, "playId": "fe7a1761-c0bb-3ae6-996c-afbfb0c7c92e", "inning": 4, "halfInning": "top", "atBatIndex": 24, "pitchInPa": 1, "paResult": "Double"}, {"pitcher": "Brandon Sproat", "pitcherId": 687075, "batter": "Lenyn Sosa", "batterId": 672820, "pitchType": "Sinker", "call": "Ball", "outcome": "ball", "pX": 1.496, "pZ": 2.3017, "szTop": 3.153, "szBottom": 1.591, "startSpeed": 95.3, "spinRate": 2033, "playId": "1c6bd5b8-8e74-314a-a83b-40dd269a64db", "inning": 4, "halfInning": "top", "atBatIndex": 24, "pitchInPa": 2, "paResult": "Double"}, {"pitcher": "Brandon Sproat", "pitcherId": 687075, "batter": "Lenyn Sosa", "batterId": 672820, "pitchType": "Sinker", "call": "Ball", "outcome": "ball", "pX": 1.5397, "pZ": 1.3561, "szTop": 3.153, "szBottom": 1.591, "startSpeed": 94.5, "spinRate": 1982, "playId": "e6053e37-395c-3bec-8add-b6164d85f791", "inning": 4, "halfInning": "top", "atBatIndex": 24, "pitchInPa": 3, "paResult": "Double"}, {"pitcher": "Brandon Sproat", "pitcherId": 687075, "batter": "Lenyn Sosa", "batterId": 672820, "pitchType": "Cutter", "call": "In play, no out", "outcome": "inplay", "pX": -0.2079, "pZ": 2.3463, "szTop": 3.153, "szBottom": 1.591, "startSpeed": 92.8, "spinRate": 2072, "playId": "cc44453e-0091-3e54-b74d-4b02cbb9d32a", "inning": 4, "halfInning": "top", "atBatIndex": 24, "pitchInPa": 4, "paResult": "Double", "launchSpeed": 104.4, "launchAngle": 22.0, "trajectory": "fly_ball"}, {"pitcher": "Brandon Sproat", "pitcherId": 687075, "batter": "Kazuma Okamoto", "batterId": 672960, "pitchType": "Sweeper", "call": "Called Strike", "outcome": "strike", "pX": -0.094, "pZ": 2.0379, "szTop": 3.256, "szBottom": 1.643, "startSpeed": 88.0, "spinRate": 2378, "playId": "e420195c-4f16-390b-adb9-a69be8dd05d9", "inning": 4, "halfInning": "top", "atBatIndex": 25, "pitchInPa": 1, "paResult": "Strikeout"}, {"pitcher": "Brandon Sproat", "pitcherId": 687075, "batter": "Kazuma Okamoto", "batterId": 672960, "pitchType": "Sweeper", "call": "Ball", "outcome": "ball", "pX": 1.8303, "pZ": 1.1875, "szTop": 3.256, "szBottom": 1.643, "startSpeed": 85.6, "spinRate": 2442, "playId": "d11dc66e-e222-3d77-a66d-657d73617fd3", "inning": 4, "halfInning": "top", "atBatIndex": 25, "pitchInPa": 2, "paResult": "Strikeout"}, {"pitcher": "Brandon Sproat", "pitcherId": 687075, "batter": "Kazuma Okamoto", "batterId": 672960, "pitchType": "Sweeper", "call": "Swinging Strike", "outcome": "strike", "pX": 0.6762, "pZ": 1.6617, "szTop": 3.256, "szBottom": 1.643, "startSpeed": 86.9, "spinRate": 2417, "playId": "9c473500-0dac-322f-bd14-8258a7d5d65f", "inning": 4, "halfInning": "top", "atBatIndex": 25, "pitchInPa": 3, "paResult": "Strikeout"}, {"pitcher": "Brandon Sproat", "pitcherId": 687075, "batter": "Kazuma Okamoto", "batterId": 672960, "pitchType": "Four-Seam Fastball", "call": "Swinging Strike", "outcome": "strike", "pX": 0.1132, "pZ": 3.3404, "szTop": 3.256, "szBottom": 1.643, "startSpeed": 98.0, "spinRate": 2048, "playId": "b6ec45fe-3438-3432-936e-673c84b5cc75", "inning": 4, "halfInning": "top", "atBatIndex": 25, "pitchInPa": 4, "paResult": "Strikeout"}, {"pitcher": "Patrick Corbin", "pitcherId": 571578, "batter": "Brice Turang", "batterId": 668930, "pitchType": "Four-Seam Fastball", "call": "Ball", "outcome": "ball", "pX": -0.8205, "pZ": 4.1308, "szTop": 3.21, "szBottom": 1.62, "startSpeed": 89.5, "spinRate": 2045, "playId": "5b481746-9bfe-3b28-a1a3-d962c130b9d4", "inning": 4, "halfInning": "bottom", "atBatIndex": 26, "pitchInPa": 1, "paResult": "Double"}, {"pitcher": "Patrick Corbin", "pitcherId": 571578, "batter": "Brice Turang", "batterId": 668930, "pitchType": "Cutter", "call": "Called Strike", "outcome": "strike", "pX": 0.3853, "pZ": 3.0713, "szTop": 3.21, "szBottom": 1.62, "startSpeed": 84.8, "spinRate": 2256, "playId": "36326b27-2170-36e7-bc5e-8ab4ff14bbba", "inning": 4, "halfInning": "bottom", "atBatIndex": 26, "pitchInPa": 2, "paResult": "Double"}, {"pitcher": "Patrick Corbin", "pitcherId": 571578, "batter": "Brice Turang", "batterId": 668930, "pitchType": "Sinker", "call": "Ball", "outcome": "ball", "pX": -0.0672, "pZ": 4.1208, "szTop": 3.21, "szBottom": 1.62, "startSpeed": 90.4, "spinRate": 1980, "playId": "383145ae-df07-3372-8da9-2a3f77d6a808", "inning": 4, "halfInning": "bottom", "atBatIndex": 26, "pitchInPa": 3, "paResult": "Double"}, {"pitcher": "Patrick Corbin", "pitcherId": 571578, "batter": "Brice Turang", "batterId": 668930, "pitchType": "Slider", "call": "Ball", "outcome": "ball", "pX": -0.6873, "pZ": 1.3766, "szTop": 3.21, "szBottom": 1.62, "startSpeed": 78.9, "spinRate": 2192, "playId": "946042a2-e1f1-340f-bd29-0b8e0eee6e07", "inning": 4, "halfInning": "bottom", "atBatIndex": 26, "pitchInPa": 4, "paResult": "Double"}, {"pitcher": "Patrick Corbin", "pitcherId": 571578, "batter": "Brice Turang", "batterId": 668930, "pitchType": "Cutter", "call": "Called Strike", "outcome": "strike", "pX": 0.0542, "pZ": 3.2727, "szTop": 3.21, "szBottom": 1.62, "startSpeed": 84.1, "spinRate": 2193, "playId": "90538c1a-54ec-3721-804a-744ee25490b2", "inning": 4, "halfInning": "bottom", "atBatIndex": 26, "pitchInPa": 5, "paResult": "Double"}, {"pitcher": "Patrick Corbin", "pitcherId": 571578, "batter": "Brice Turang", "batterId": 668930, "pitchType": "Cutter", "call": "Foul", "outcome": "strike", "pX": -0.3418, "pZ": 2.577, "szTop": 3.21, "szBottom": 1.62, "startSpeed": 85.8, "spinRate": 2306, "playId": "354aefa7-d1a9-3eca-9267-6b5060ebf90f", "inning": 4, "halfInning": "bottom", "atBatIndex": 26, "pitchInPa": 6, "paResult": "Double"}, {"pitcher": "Patrick Corbin", "pitcherId": 571578, "batter": "Brice Turang", "batterId": 668930, "pitchType": "Sinker", "call": "In play, no out", "outcome": "inplay", "pX": -0.1805, "pZ": 2.719, "szTop": 3.21, "szBottom": 1.62, "startSpeed": 90.9, "spinRate": 1945, "playId": "db2cc493-4370-376d-abb0-5f7065b8d2ac", "inning": 4, "halfInning": "bottom", "atBatIndex": 26, "pitchInPa": 7, "paResult": "Double", "launchSpeed": 109.4, "launchAngle": 21.0, "trajectory": "line_drive"}, {"pitcher": "Patrick Corbin", "pitcherId": 571578, "batter": "William Contreras", "batterId": 661388, "pitchType": "Changeup", "call": "Ball In Dirt", "outcome": "ball", "pX": -0.5013, "pZ": 0.8492, "szTop": 3.133, "szBottom": 1.581, "startSpeed": 79.1, "spinRate": 1173, "playId": "e452b4c7-dfb4-3c60-a3e0-a33c8a90e971", "inning": 4, "halfInning": "bottom", "atBatIndex": 27, "pitchInPa": 1, "paResult": "Single"}, {"pitcher": "Patrick Corbin", "pitcherId": 571578, "batter": "William Contreras", "batterId": 661388, "pitchType": "Sinker", "call": "Ball", "outcome": "ball", "pX": -0.8985, "pZ": 2.0405, "szTop": 3.133, "szBottom": 1.581, "startSpeed": 92.1, "spinRate": 2085, "playId": "5fa1de6f-0cbf-3791-8a5a-7de81bf51773", "inning": 4, "halfInning": "bottom", "atBatIndex": 27, "pitchInPa": 2, "paResult": "Single"}, {"pitcher": "Patrick Corbin", "pitcherId": 571578, "batter": "William Contreras", "batterId": 661388, "pitchType": "Sinker", "call": "Called Strike", "outcome": "strike", "pX": -0.2975, "pZ": 1.6579, "szTop": 3.133, "szBottom": 1.581, "startSpeed": 92.2, "spinRate": 2156, "playId": "4989422f-14df-3a5d-b0d2-cd3aa30ed40c", "inning": 4, "halfInning": "bottom", "atBatIndex": 27, "pitchInPa": 3, "paResult": "Single"}, {"pitcher": "Patrick Corbin", "pitcherId": 571578, "batter": "William Contreras", "batterId": 661388, "pitchType": "Cutter", "call": "In play, no out", "outcome": "inplay", "pX": 0.3382, "pZ": 2.8807, "szTop": 3.133, "szBottom": 1.581, "startSpeed": 86.8, "spinRate": 2303, "playId": "396a6b28-6352-3a97-a9e7-02e18740743a", "inning": 4, "halfInning": "bottom", "atBatIndex": 27, "pitchInPa": 4, "paResult": "Single", "launchSpeed": 109.5, "launchAngle": 13.0, "trajectory": "line_drive"}, {"pitcher": "Patrick Corbin", "pitcherId": 571578, "batter": "Gary S\u00e1nchez", "batterId": 596142, "pitchType": "Sinker", "call": "In play, out(s)", "outcome": "inplay", "pX": 0.8082, "pZ": 2.6133, "szTop": 3.311, "szBottom": 1.671, "startSpeed": 91.2, "spinRate": 2020, "playId": "8fdbd9bd-b95e-3de6-8255-07b4fc7aa91b", "inning": 4, "halfInning": "bottom", "atBatIndex": 28, "pitchInPa": 1, "paResult": "Flyout", "launchSpeed": 80.2, "launchAngle": 43.0, "trajectory": "fly_ball"}, {"pitcher": "Patrick Corbin", "pitcherId": 571578, "batter": "Luis Rengifo", "batterId": 650859, "pitchType": "Cutter", "call": "Called Strike", "outcome": "strike", "pX": -0.4287, "pZ": 3.2937, "szTop": 3.087, "szBottom": 1.558, "startSpeed": 86.3, "spinRate": 2249, "playId": "4564219b-2dd2-3eb5-a588-c015b4c51916", "inning": 4, "halfInning": "bottom", "atBatIndex": 29, "pitchInPa": 1, "paResult": "Sac Fly"}, {"pitcher": "Patrick Corbin", "pitcherId": 571578, "batter": "Luis Rengifo", "batterId": 650859, "pitchType": "Changeup", "call": "In play, run(s)", "outcome": "inplay", "pX": 0.8211, "pZ": 2.7376, "szTop": 3.087, "szBottom": 1.558, "startSpeed": 80.1, "spinRate": 1109, "playId": "66b46e61-ae02-3e10-9c1c-8f28b1e8c678", "inning": 4, "halfInning": "bottom", "atBatIndex": 29, "pitchInPa": 2, "paResult": "Sac Fly", "launchSpeed": 76.1, "launchAngle": 27.0, "trajectory": "line_drive"}, {"pitcher": "Patrick Corbin", "pitcherId": 571578, "batter": "Luis Matos", "batterId": 682641, "pitchType": "Sinker", "call": "Ball In Dirt", "outcome": "ball", "pX": -1.2671, "pZ": 1.1825, "szTop": 3.168, "szBottom": 1.599, "startSpeed": 91.8, "spinRate": 2103, "playId": "bdd89f8e-9450-30f8-8613-c08c27d67fbf", "inning": 4, "halfInning": "bottom", "atBatIndex": 30, "pitchInPa": 1, "paResult": "Groundout"}, {"pitcher": "Patrick Corbin", "pitcherId": 571578, "batter": "Luis Matos", "batterId": 682641, "pitchType": "Cutter", "call": "Foul", "outcome": "strike", "pX": -1.2339, "pZ": 2.522, "szTop": 3.168, "szBottom": 1.599, "startSpeed": 86.2, "spinRate": 2250, "playId": "953158bf-cd68-304e-905a-2d361d60c499", "inning": 4, "halfInning": "bottom", "atBatIndex": 30, "pitchInPa": 2, "paResult": "Groundout"}, {"pitcher": "Patrick Corbin", "pitcherId": 571578, "batter": "Luis Matos", "batterId": 682641, "pitchType": "Changeup", "call": "In play, out(s)", "outcome": "inplay", "pX": 0.7819, "pZ": 1.4631, "szTop": 3.168, "szBottom": 1.599, "startSpeed": 78.9, "spinRate": 1030, "playId": "97aff172-e285-3093-9d46-7e849044f11d", "inning": 4, "halfInning": "bottom", "atBatIndex": 30, "pitchInPa": 3, "paResult": "Groundout", "launchSpeed": 75.1, "launchAngle": -7.0, "trajectory": "ground_ball"}, {"pitcher": "Brandon Sproat", "pitcherId": 687075, "batter": "Andr\u00e9s Gim\u00e9nez", "batterId": 665926, "pitchType": "Four-Seam Fastball", "call": "Called Strike", "outcome": "strike", "pX": 0.3228, "pZ": 1.5447, "szTop": 3.165, "szBottom": 1.597, "startSpeed": 95.7, "spinRate": 2075, "playId": "8f60b75e-59fd-3f70-bf52-f8a7fe3c4ab4", "inning": 5, "halfInning": "top", "atBatIndex": 31, "pitchInPa": 1, "paResult": "Strikeout"}, {"pitcher": "Brandon Sproat", "pitcherId": 687075, "batter": "Andr\u00e9s Gim\u00e9nez", "batterId": 665926, "pitchType": "Four-Seam Fastball", "call": "Swinging Strike", "outcome": "strike", "pX": -1.2238, "pZ": 2.1201, "szTop": 3.165, "szBottom": 1.597, "startSpeed": 95.2, "spinRate": 2029, "playId": "445f0305-f4f1-3694-acff-1d2ddb90f0dc", "inning": 5, "halfInning": "top", "atBatIndex": 31, "pitchInPa": 2, "paResult": "Strikeout"}, {"pitcher": "Brandon Sproat", "pitcherId": 687075, "batter": "Andr\u00e9s Gim\u00e9nez", "batterId": 665926, "pitchType": "Cutter", "call": "Foul", "outcome": "strike", "pX": 0.7978, "pZ": 3.0297, "szTop": 3.165, "szBottom": 1.597, "startSpeed": 91.6, "spinRate": 2112, "playId": "9db5e675-5372-380b-80da-27776cd57ca1", "inning": 5, "halfInning": "top", "atBatIndex": 31, "pitchInPa": 3, "paResult": "Strikeout"}, {"pitcher": "Brandon Sproat", "pitcherId": 687075, "batter": "Andr\u00e9s Gim\u00e9nez", "batterId": 665926, "pitchType": "Curveball", "call": "Foul", "outcome": "strike", "pX": 0.2061, "pZ": 0.5345, "szTop": 3.165, "szBottom": 1.597, "startSpeed": 82.6, "spinRate": 2412, "playId": "4f899f83-d729-35b3-a498-b1916210069b", "inning": 5, "halfInning": "top", "atBatIndex": 31, "pitchInPa": 4, "paResult": "Strikeout"}, {"pitcher": "Brandon Sproat", "pitcherId": 687075, "batter": "Andr\u00e9s Gim\u00e9nez", "batterId": 665926, "pitchType": "Curveball", "call": "Ball", "outcome": "ball", "pX": 0.6668, "pZ": -0.1823, "szTop": 3.165, "szBottom": 1.597, "startSpeed": 82.7, "spinRate": 2553, "playId": "a5881cff-a188-3fa0-a2ce-24c7f41f29a0", "inning": 5, "halfInning": "top", "atBatIndex": 31, "pitchInPa": 5, "paResult": "Strikeout"}, {"pitcher": "Brandon Sproat", "pitcherId": 687075, "batter": "Andr\u00e9s Gim\u00e9nez", "batterId": 665926, "pitchType": "Four-Seam Fastball", "call": "Swinging Strike", "outcome": "strike", "pX": 0.298, "pZ": 1.8189, "szTop": 3.165, "szBottom": 1.597, "startSpeed": 97.6, "spinRate": 2085, "playId": "e6cd2a09-05c3-3bec-8feb-a33ec4133eff", "inning": 5, "halfInning": "top", "atBatIndex": 31, "pitchInPa": 6, "paResult": "Strikeout"}, {"pitcher": "Brandon Sproat", "pitcherId": 687075, "batter": "Ernie Clement", "batterId": 676391, "pitchType": "Cutter", "call": "In play, out(s)", "outcome": "inplay", "pX": -0.1733, "pZ": 2.6494, "szTop": 3.191, "szBottom": 1.61, "startSpeed": 91.9, "spinRate": 2136, "playId": "38288b0f-3e7d-3451-9ea4-fba61d6f6012", "inning": 5, "halfInning": "top", "atBatIndex": 32, "pitchInPa": 1, "paResult": "Lineout", "launchSpeed": 100.2, "launchAngle": 22.0, "trajectory": "line_drive"}, {"pitcher": "Brandon Sproat", "pitcherId": 687075, "batter": "Tyler Heineman", "batterId": 623168, "pitchType": "Four-Seam Fastball", "call": "Called Strike", "outcome": "strike", "pX": 0.0834, "pZ": 1.9154, "szTop": 3.11, "szBottom": 1.57, "startSpeed": 97.5, "spinRate": 2061, "playId": "47b297f7-c276-3a96-847c-7984144a78a8", "inning": 5, "halfInning": "top", "atBatIndex": 33, "pitchInPa": 1, "paResult": "Strikeout"}, {"pitcher": "Brandon Sproat", "pitcherId": 687075, "batter": "Tyler Heineman", "batterId": 623168, "pitchType": "Four-Seam Fastball", "call": "Foul", "outcome": "strike", "pX": -0.8191, "pZ": 2.8877, "szTop": 3.11, "szBottom": 1.57, "startSpeed": 96.9, "spinRate": 2099, "playId": "b713549a-1599-33e0-bb17-0ba06f63e332", "inning": 5, "halfInning": "top", "atBatIndex": 33, "pitchInPa": 2, "paResult": "Strikeout"}, {"pitcher": "Brandon Sproat", "pitcherId": 687075, "batter": "Tyler Heineman", "batterId": 623168, "pitchType": "Curveball", "call": "Swinging Strike (Blocked)", "outcome": "strike", "pX": 0.2729, "pZ": 0.6281, "szTop": 3.11, "szBottom": 1.57, "startSpeed": 85.5, "spinRate": 2635, "playId": "7253ae4e-3810-30f3-8037-84d7413d2bea", "inning": 5, "halfInning": "top", "atBatIndex": 33, "pitchInPa": 3, "paResult": "Strikeout"}, {"pitcher": "Patrick Corbin", "pitcherId": 571578, "batter": "Greg Jones", "batterId": 675659, "pitchType": "Cutter", "call": "Ball", "outcome": "ball", "pX": -0.0292, "pZ": 3.4328, "szTop": 3.203, "szBottom": 1.617, "startSpeed": 85.2, "spinRate": 2238, "playId": "fcffea6b-49b4-3743-a442-847cc898f7ca", "inning": 5, "halfInning": "bottom", "atBatIndex": 34, "pitchInPa": 1, "paResult": "Single"}, {"pitcher": "Patrick Corbin", "pitcherId": 571578, "batter": "Greg Jones", "batterId": 675659, "pitchType": "Sinker", "call": "Foul", "outcome": "strike", "pX": 0.3791, "pZ": 2.8023, "szTop": 3.203, "szBottom": 1.617, "startSpeed": 90.7, "spinRate": 2085, "playId": "ad1b5f07-ff65-3313-84b6-b55bfa7dfd44", "inning": 5, "halfInning": "bottom", "atBatIndex": 34, "pitchInPa": 2, "paResult": "Single"}, {"pitcher": "Patrick Corbin", "pitcherId": 571578, "batter": "Greg Jones", "batterId": 675659, "pitchType": "Slider", "call": "In play, no out", "outcome": "inplay", "pX": 0.5124, "pZ": 1.8848, "szTop": 3.203, "szBottom": 1.617, "startSpeed": 78.5, "spinRate": 2083, "playId": "98785a02-8545-3994-a555-4d09ef705fe9", "inning": 5, "halfInning": "bottom", "atBatIndex": 34, "pitchInPa": 3, "paResult": "Single", "launchSpeed": 95.6, "launchAngle": 15.0, "trajectory": "line_drive"}, {"pitcher": "Patrick Corbin", "pitcherId": 571578, "batter": "David Hamilton", "batterId": 666152, "pitchType": "Four-Seam Fastball", "call": "Ball", "outcome": "ball", "pX": -1.0311, "pZ": 3.5424, "szTop": 3.135, "szBottom": 1.582, "startSpeed": 88.6, "spinRate": 2043, "playId": "a33eccfe-2729-36bd-9b14-b8ec90cc6d49", "inning": 5, "halfInning": "bottom", "atBatIndex": 35, "pitchInPa": 1, "paResult": "Strikeout"}, {"pitcher": "Patrick Corbin", "pitcherId": 571578, "batter": "David Hamilton", "batterId": 666152, "pitchType": "Slider", "call": "Swinging Strike", "outcome": "strike", "pX": -0.6387, "pZ": 1.5017, "szTop": 3.135, "szBottom": 1.582, "startSpeed": 77.2, "spinRate": 2117, "playId": "86f9086b-d944-3586-975b-bb69eb8bddef", "inning": 5, "halfInning": "bottom", "atBatIndex": 35, "pitchInPa": 2, "paResult": "Strikeout"}, {"pitcher": "Patrick Corbin", "pitcherId": 571578, "batter": "David Hamilton", "batterId": 666152, "pitchType": "Slider", "call": "Called Strike", "outcome": "strike", "pX": -0.0296, "pZ": 1.3876, "szTop": 3.135, "szBottom": 1.582, "startSpeed": 76.5, "spinRate": 2152, "playId": "689dde2d-2748-318a-ae30-fa9855dc6a05", "inning": 5, "halfInning": "bottom", "atBatIndex": 35, "pitchInPa": 3, "paResult": "Strikeout"}, {"pitcher": "Patrick Corbin", "pitcherId": 571578, "batter": "David Hamilton", "batterId": 666152, "pitchType": "Slider", "call": "Swinging Strike (Blocked)", "outcome": "strike", "pX": -1.2843, "pZ": 0.1468, "szTop": 3.135, "szBottom": 1.582, "startSpeed": 80.5, "spinRate": 2326, "playId": "8c7251e7-0999-39d2-9290-3b514422c596", "inning": 5, "halfInning": "bottom", "atBatIndex": 35, "pitchInPa": 4, "paResult": "Strikeout"}, {"pitcher": "Patrick Corbin", "pitcherId": 571578, "batter": "Joey Ortiz", "batterId": 687401, "pitchType": "Cutter", "call": "Ball", "outcome": "ball", "pX": -0.8156, "pZ": 0.9985, "szTop": 3.137, "szBottom": 1.583, "startSpeed": 85.1, "spinRate": 2271, "playId": "1392bff7-63bc-31f4-a584-fcfb9ff6aa46", "inning": 5, "halfInning": "bottom", "atBatIndex": 36, "pitchInPa": 1, "paResult": "Strikeout"}, {"pitcher": "Patrick Corbin", "pitcherId": 571578, "batter": "Joey Ortiz", "batterId": 687401, "pitchType": "Sinker", "call": "Called Strike", "outcome": "strike", "pX": 0.3422, "pZ": 2.2103, "szTop": 3.137, "szBottom": 1.583, "startSpeed": 90.2, "spinRate": 2130, "playId": "82315281-3e42-3a71-bbda-01a371e976aa", "inning": 5, "halfInning": "bottom", "atBatIndex": 36, "pitchInPa": 2, "paResult": "Strikeout"}, {"pitcher": "Patrick Corbin", "pitcherId": 571578, "batter": "Joey Ortiz", "batterId": 687401, "pitchType": "Changeup", "call": "Swinging Strike", "outcome": "strike", "pX": -0.726, "pZ": 2.7103, "szTop": 3.137, "szBottom": 1.583, "startSpeed": 80.0, "spinRate": 1048, "playId": "d83e2847-d400-3a20-a52c-fca4b24531f0", "inning": 5, "halfInning": "bottom", "atBatIndex": 36, "pitchInPa": 3, "paResult": "Strikeout"}, {"pitcher": "Patrick Corbin", "pitcherId": 571578, "batter": "Joey Ortiz", "batterId": 687401, "pitchType": "Sinker", "call": "Foul", "outcome": "strike", "pX": -0.3118, "pZ": 2.6298, "szTop": 3.137, "szBottom": 1.583, "startSpeed": 90.4, "spinRate": 2080, "playId": "a9f1a63a-3288-36d5-9abb-40b6d512d2a3", "inning": 5, "halfInning": "bottom", "atBatIndex": 36, "pitchInPa": 4, "paResult": "Strikeout"}, {"pitcher": "Patrick Corbin", "pitcherId": 571578, "batter": "Joey Ortiz", "batterId": 687401, "pitchType": "Slider", "call": "Ball", "outcome": "ball", "pX": 0.6943, "pZ": -0.2844, "szTop": 3.137, "szBottom": 1.583, "startSpeed": 81.4, "spinRate": 2309, "playId": "e0f6274d-68df-351b-a3a7-316d6124d9c0", "inning": 5, "halfInning": "bottom", "atBatIndex": 36, "pitchInPa": 5, "paResult": "Strikeout"}, {"pitcher": "Patrick Corbin", "pitcherId": 571578, "batter": "Joey Ortiz", "batterId": 687401, "pitchType": "Slider", "call": "Swinging Strike (Blocked)", "outcome": "strike", "pX": -0.034, "pZ": 0.4401, "szTop": 3.137, "szBottom": 1.583, "startSpeed": 78.6, "spinRate": 2169, "playId": "cdd7ff65-6192-3ce7-afc8-525583253666", "inning": 5, "halfInning": "bottom", "atBatIndex": 36, "pitchInPa": 6, "paResult": "Strikeout"}, {"pitcher": "Brandon Sproat", "pitcherId": 687075, "batter": "Davis Schneider", "batterId": 676914, "pitchType": "Sinker", "call": "Ball", "outcome": "ball", "pX": -0.0692, "pZ": 0.2293, "szTop": 3.045, "szBottom": 1.537, "startSpeed": 94.7, "spinRate": 1892, "playId": "839efd90-5e84-3849-b343-933ce73c11b2", "inning": 6, "halfInning": "top", "atBatIndex": 37, "pitchInPa": 1, "paResult": "Walk"}, {"pitcher": "Brandon Sproat", "pitcherId": 687075, "batter": "Davis Schneider", "batterId": 676914, "pitchType": "Sinker", "call": "Ball", "outcome": "ball", "pX": 1.1279, "pZ": 0.8919, "szTop": 3.045, "szBottom": 1.537, "startSpeed": 95.4, "spinRate": 1945, "playId": "32cacf0c-bcb8-3895-bdb5-4a351635776b", "inning": 6, "halfInning": "top", "atBatIndex": 37, "pitchInPa": 2, "paResult": "Walk"}, {"pitcher": "Brandon Sproat", "pitcherId": 687075, "batter": "Davis Schneider", "batterId": 676914, "pitchType": "Four-Seam Fastball", "call": "Ball", "outcome": "ball", "pX": 1.4011, "pZ": 2.1481, "szTop": 3.045, "szBottom": 1.537, "startSpeed": 96.1, "spinRate": 2055, "playId": "e7f4cb5b-1f61-3c26-badf-ed0d7da58338", "inning": 6, "halfInning": "top", "atBatIndex": 37, "pitchInPa": 3, "paResult": "Walk"}, {"pitcher": "Brandon Sproat", "pitcherId": 687075, "batter": "Davis Schneider", "batterId": 676914, "pitchType": "Cutter", "call": "Called Strike", "outcome": "strike", "pX": 0.6327, "pZ": 2.6009, "szTop": 3.045, "szBottom": 1.537, "startSpeed": 93.1, "spinRate": 2132, "playId": "d518702b-7a83-3727-81ae-9130b9861eea", "inning": 6, "halfInning": "top", "atBatIndex": 37, "pitchInPa": 4, "paResult": "Walk"}, {"pitcher": "Brandon Sproat", "pitcherId": 687075, "batter": "Davis Schneider", "batterId": 676914, "pitchType": "Cutter", "call": "Foul", "outcome": "strike", "pX": -0.7793, "pZ": 1.9136, "szTop": 3.045, "szBottom": 1.537, "startSpeed": 92.7, "spinRate": 2081, "playId": "be5745e3-4d80-3cf6-ba76-0da3da042375", "inning": 6, "halfInning": "top", "atBatIndex": 37, "pitchInPa": 5, "paResult": "Walk"}, {"pitcher": "Brandon Sproat", "pitcherId": 687075, "batter": "Davis Schneider", "batterId": 676914, "pitchType": "Cutter", "call": "Ball", "outcome": "ball", "pX": 2.4859, "pZ": 1.7842, "szTop": 3.045, "szBottom": 1.537, "startSpeed": 92.8, "spinRate": 2222, "playId": "305ba462-6569-334e-84f4-fb61c741b639", "inning": 6, "halfInning": "top", "atBatIndex": 37, "pitchInPa": 6, "paResult": "Walk"}, {"pitcher": "Brandon Sproat", "pitcherId": 687075, "batter": "Daulton Varsho", "batterId": 662139, "pitchType": "Sinker", "call": "In play, no out", "outcome": "inplay", "pX": -0.7938, "pZ": 2.1617, "szTop": 3.037, "szBottom": 1.532, "startSpeed": 95.3, "spinRate": 1768, "playId": "293d694e-ca15-3640-9800-190fbae27617", "inning": 6, "halfInning": "top", "atBatIndex": 38, "pitchInPa": 1, "paResult": "Single", "launchSpeed": 75.4, "launchAngle": 15.0, "trajectory": "line_drive"}, {"pitcher": "Brandon Sproat", "pitcherId": 687075, "batter": "Vladimir Guerrero Jr.", "batterId": 665489, "pitchType": "Sweeper", "call": "In play, out(s)", "outcome": "inplay", "pX": 0.2798, "pZ": 2.145, "szTop": 3.209, "szBottom": 1.619, "startSpeed": 85.2, "spinRate": 2296, "playId": "4b8b74cb-bd91-3715-b5d9-038ee201f193", "inning": 6, "halfInning": "top", "atBatIndex": 39, "pitchInPa": 1, "paResult": "Grounded Into DP", "launchSpeed": 83.9, "launchAngle": -0.0, "trajectory": "ground_ball"}, {"pitcher": "Brandon Sproat", "pitcherId": 687075, "batter": "Jes\u00fas S\u00e1nchez", "batterId": 660821, "pitchType": "Curveball", "call": "Swinging Strike", "outcome": "strike", "pX": 0.1092, "pZ": 2.8972, "szTop": 3.335, "szBottom": 1.683, "startSpeed": 84.2, "spinRate": 2595, "playId": "ccd72d7c-447e-35a7-a2bf-550dc2efb3e0", "inning": 6, "halfInning": "top", "atBatIndex": 40, "pitchInPa": 1, "paResult": "Lineout"}, {"pitcher": "Brandon Sproat", "pitcherId": 687075, "batter": "Jes\u00fas S\u00e1nchez", "batterId": 660821, "pitchType": "Curveball", "call": "In play, out(s)", "outcome": "inplay", "pX": -0.4427, "pZ": 1.5923, "szTop": 3.335, "szBottom": 1.683, "startSpeed": 83.5, "spinRate": 2602, "playId": "c83feb93-5ebb-3580-8559-aea7fc19221b", "inning": 6, "halfInning": "top", "atBatIndex": 40, "pitchInPa": 2, "paResult": "Lineout", "launchSpeed": 99.1, "launchAngle": 19.0, "trajectory": "line_drive"}, {"pitcher": "Patrick Corbin", "pitcherId": 571578, "batter": "Brandon Lockridge", "batterId": 663604, "pitchType": "Slider", "call": "Foul", "outcome": "strike", "pX": 0.1018, "pZ": 2.7708, "szTop": 3.226, "szBottom": 1.628, "startSpeed": 71.0, "spinRate": 2027, "playId": "a909bc68-af57-3db5-9e85-a90339523ca5", "inning": 6, "halfInning": "bottom", "atBatIndex": 41, "pitchInPa": 1, "paResult": "Groundout"}, {"pitcher": "Patrick Corbin", "pitcherId": 571578, "batter": "Brandon Lockridge", "batterId": 663604, "pitchType": "Changeup", "call": "Ball", "outcome": "ball", "pX": 0.5623, "pZ": 3.3288, "szTop": 3.226, "szBottom": 1.628, "startSpeed": 77.9, "spinRate": 1049, "playId": "3fdd0343-73b3-3431-9015-04f8996f23f9", "inning": 6, "halfInning": "bottom", "atBatIndex": 41, "pitchInPa": 2, "paResult": "Groundout"}, {"pitcher": "Patrick Corbin", "pitcherId": 571578, "batter": "Brandon Lockridge", "batterId": 663604, "pitchType": "Cutter", "call": "Ball", "outcome": "ball", "pX": -1.5154, "pZ": 1.9424, "szTop": 3.226, "szBottom": 1.628, "startSpeed": 86.7, "spinRate": 2328, "playId": "a5f01143-f2e3-3501-a1b4-ca13c2b9ea9d", "inning": 6, "halfInning": "bottom", "atBatIndex": 41, "pitchInPa": 3, "paResult": "Groundout"}, {"pitcher": "Patrick Corbin", "pitcherId": 571578, "batter": "Brandon Lockridge", "batterId": 663604, "pitchType": "Sinker", "call": "Foul", "outcome": "strike", "pX": -0.2408, "pZ": 1.7057, "szTop": 3.226, "szBottom": 1.628, "startSpeed": 90.4, "spinRate": 2044, "playId": "19ff915f-d571-347b-aaab-2711808c04e4", "inning": 6, "halfInning": "bottom", "atBatIndex": 41, "pitchInPa": 4, "paResult": "Groundout"}, {"pitcher": "Patrick Corbin", "pitcherId": 571578, "batter": "Brandon Lockridge", "batterId": 663604, "pitchType": "Cutter", "call": "Ball", "outcome": "ball", "pX": 1.3239, "pZ": 3.5786, "szTop": 3.226, "szBottom": 1.628, "startSpeed": 84.9, "spinRate": 2308, "playId": "7503fb28-1930-3538-968b-96bf036e56c9", "inning": 6, "halfInning": "bottom", "atBatIndex": 41, "pitchInPa": 5, "paResult": "Groundout"}, {"pitcher": "Patrick Corbin", "pitcherId": 571578, "batter": "Brandon Lockridge", "batterId": 663604, "pitchType": "Sinker", "call": "In play, out(s)", "outcome": "inplay", "pX": 0.8985, "pZ": 2.3592, "szTop": 3.226, "szBottom": 1.628, "startSpeed": 89.9, "spinRate": 1957, "playId": "4a621373-c085-3361-9eb6-7257a39f78d9", "inning": 6, "halfInning": "bottom", "atBatIndex": 41, "pitchInPa": 6, "paResult": "Groundout", "launchSpeed": 80.7, "launchAngle": -30.0, "trajectory": "ground_ball"}, {"pitcher": "Patrick Corbin", "pitcherId": 571578, "batter": "Brice Turang", "batterId": 668930, "pitchType": "Slider", "call": "Called Strike", "outcome": "strike", "pX": 0.064, "pZ": 2.0657, "szTop": 3.21, "szBottom": 1.62, "startSpeed": 75.8, "spinRate": 2083, "playId": "993b048a-cf56-3ae4-a6bb-1b056cc85d71", "inning": 6, "halfInning": "bottom", "atBatIndex": 42, "pitchInPa": 1, "paResult": "Strikeout"}, {"pitcher": "Patrick Corbin", "pitcherId": 571578, "batter": "Brice Turang", "batterId": 668930, "pitchType": "Sinker", "call": "Foul", "outcome": "strike", "pX": 0.332, "pZ": 2.9865, "szTop": 3.21, "szBottom": 1.62, "startSpeed": 90.2, "spinRate": 2062, "playId": "e430b326-bcf5-3478-bf2b-d07f2dea142e", "inning": 6, "halfInning": "bottom", "atBatIndex": 42, "pitchInPa": 2, "paResult": "Strikeout"}, {"pitcher": "Patrick Corbin", "pitcherId": 571578, "batter": "Brice Turang", "batterId": 668930, "pitchType": "Slider", "call": "Swinging Strike", "outcome": "strike", "pX": -1.1294, "pZ": 1.5078, "szTop": 3.21, "szBottom": 1.62, "startSpeed": 81.8, "spinRate": 2187, "playId": "7135f090-38b4-3c73-b93e-2d4e210207b9", "inning": 6, "halfInning": "bottom", "atBatIndex": 42, "pitchInPa": 3, "paResult": "Strikeout"}, {"pitcher": "Tommy Nance", "pitcherId": 667297, "batter": "William Contreras", "batterId": 661388, "pitchType": "Slider", "call": "Foul", "outcome": "strike", "pX": 0.0884, "pZ": 1.8988, "szTop": 3.133, "szBottom": 1.581, "startSpeed": 89.4, "spinRate": 2507, "playId": "01507934-33bc-3506-810b-c19ebf36d9e4", "inning": 6, "halfInning": "bottom", "atBatIndex": 43, "pitchInPa": 1, "paResult": "Single"}, {"pitcher": "Tommy Nance", "pitcherId": 667297, "batter": "William Contreras", "batterId": 661388, "pitchType": "Slider", "call": "Ball", "outcome": "ball", "pX": 1.6799, "pZ": 3.0297, "szTop": 3.133, "szBottom": 1.581, "startSpeed": 89.0, "spinRate": 2837, "playId": "48f9fa8c-bd2d-35d4-990e-1bb1750d647b", "inning": 6, "halfInning": "bottom", "atBatIndex": 43, "pitchInPa": 2, "paResult": "Single"}, {"pitcher": "Tommy Nance", "pitcherId": 667297, "batter": "William Contreras", "batterId": 661388, "pitchType": "Sinker", "call": "In play, no out", "outcome": "inplay", "pX": 0.1527, "pZ": 2.7452, "szTop": 3.133, "szBottom": 1.581, "startSpeed": 94.2, "spinRate": 2233, "playId": "74b28c29-c455-3b38-b5c9-b67b33265010", "inning": 6, "halfInning": "bottom", "atBatIndex": 43, "pitchInPa": 3, "paResult": "Single", "launchSpeed": 104.4, "launchAngle": 12.0, "trajectory": "line_drive"}, {"pitcher": "Tommy Nance", "pitcherId": 667297, "batter": "Gary S\u00e1nchez", "batterId": 596142, "pitchType": "Slider", "call": "Ball", "outcome": "ball", "pX": 0.8788, "pZ": 2.8611, "szTop": 3.311, "szBottom": 1.671, "startSpeed": 89.4, "spinRate": 2641, "playId": "a4f23347-e812-3eb7-bc7e-8d8e6d9ade92", "inning": 6, "halfInning": "bottom", "atBatIndex": 44, "pitchInPa": 1, "paResult": "Walk"}, {"pitcher": "Tommy Nance", "pitcherId": 667297, "batter": "Gary S\u00e1nchez", "batterId": 596142, "pitchType": "Slider", "call": "Swinging Strike", "outcome": "strike", "pX": 0.5586, "pZ": 1.7025, "szTop": 3.311, "szBottom": 1.671, "startSpeed": 89.0, "spinRate": 2701, "playId": "02aebfb0-9f21-3607-b2b5-6cfe228382d1", "inning": 6, "halfInning": "bottom", "atBatIndex": 44, "pitchInPa": 2, "paResult": "Walk"}, {"pitcher": "Tommy Nance", "pitcherId": 667297, "batter": "Gary S\u00e1nchez", "batterId": 596142, "pitchType": "Sinker", "call": "Ball", "outcome": "ball", "pX": -1.2104, "pZ": 2.2222, "szTop": 3.311, "szBottom": 1.671, "startSpeed": 94.9, "spinRate": 2383, "playId": "c47fd326-d329-3846-8221-35d4d4372f7c", "inning": 6, "halfInning": "bottom", "atBatIndex": 44, "pitchInPa": 3, "paResult": "Walk"}, {"pitcher": "Tommy Nance", "pitcherId": 667297, "batter": "Gary S\u00e1nchez", "batterId": 596142, "pitchType": "Slider", "call": "Ball In Dirt", "outcome": "ball", "pX": 0.3671, "pZ": 0.6813, "szTop": 3.311, "szBottom": 1.671, "startSpeed": 89.9, "spinRate": 2650, "playId": "38d08076-cb0d-3751-a689-83c8304b4a8c", "inning": 6, "halfInning": "bottom", "atBatIndex": 44, "pitchInPa": 4, "paResult": "Walk"}, {"pitcher": "Tommy Nance", "pitcherId": 667297, "batter": "Gary S\u00e1nchez", "batterId": 596142, "pitchType": "Slider", "call": "Ball", "outcome": "ball", "pX": -0.8143, "pZ": 3.7868, "szTop": 3.311, "szBottom": 1.671, "startSpeed": 89.3, "spinRate": 2729, "playId": "350f2e72-af76-3fcb-8831-cb6d9ce6b3fe", "inning": 6, "halfInning": "bottom", "atBatIndex": 44, "pitchInPa": 5, "paResult": "Walk"}, {"pitcher": "Tommy Nance", "pitcherId": 667297, "batter": "Jake Bauers", "batterId": 641343, "pitchType": "Curveball", "call": "In play, out(s)", "outcome": "inplay", "pX": 0.314, "pZ": 2.9779, "szTop": 3.217, "szBottom": 1.624, "startSpeed": 83.8, "spinRate": 3082, "playId": "b0fd3d81-df42-39aa-989c-9c6a126c31b1", "inning": 6, "halfInning": "bottom", "atBatIndex": 45, "pitchInPa": 1, "paResult": "Lineout", "launchSpeed": 57.2, "launchAngle": 24.0, "trajectory": "line_drive"}, {"pitcher": "Brandon Sproat", "pitcherId": 687075, "batter": "Lenyn Sosa", "batterId": 672820, "pitchType": "Sinker", "call": "Called Strike", "outcome": "strike", "pX": -0.1087, "pZ": 2.158, "szTop": 3.153, "szBottom": 1.591, "startSpeed": 94.4, "spinRate": 1834, "playId": "1dff89ac-cda2-3f7f-8996-c52dad048f06", "inning": 7, "halfInning": "top", "atBatIndex": 46, "pitchInPa": 1, "paResult": "Flyout"}, {"pitcher": "Brandon Sproat", "pitcherId": 687075, "batter": "Lenyn Sosa", "batterId": 672820, "pitchType": "Sweeper", "call": "In play, out(s)", "outcome": "inplay", "pX": -0.4897, "pZ": 2.8028, "szTop": 3.153, "szBottom": 1.591, "startSpeed": 83.1, "spinRate": 2310, "playId": "4dc8099f-4152-3a22-bec9-0ebacba6d234", "inning": 7, "halfInning": "top", "atBatIndex": 46, "pitchInPa": 2, "paResult": "Flyout", "launchSpeed": 88.6, "launchAngle": 52.0, "trajectory": "fly_ball"}, {"pitcher": "Brandon Sproat", "pitcherId": 687075, "batter": "Kazuma Okamoto", "batterId": 672960, "pitchType": "Sweeper", "call": "Ball", "outcome": "ball", "pX": 1.02, "pZ": -0.0046, "szTop": 3.256, "szBottom": 1.643, "startSpeed": 85.7, "spinRate": 2348, "playId": "50d45e55-3b75-391a-a89a-b65c6af6d915", "inning": 7, "halfInning": "top", "atBatIndex": 47, "pitchInPa": 1, "paResult": "Groundout"}, {"pitcher": "Brandon Sproat", "pitcherId": 687075, "batter": "Kazuma Okamoto", "batterId": 672960, "pitchType": "Sweeper", "call": "Ball", "outcome": "ball", "pX": 1.2852, "pZ": 1.2509, "szTop": 3.256, "szBottom": 1.643, "startSpeed": 85.3, "spinRate": 2313, "playId": "67dab41a-a9ae-3a72-be0e-68ab735b5f31", "inning": 7, "halfInning": "top", "atBatIndex": 47, "pitchInPa": 2, "paResult": "Groundout"}, {"pitcher": "Brandon Sproat", "pitcherId": 687075, "batter": "Kazuma Okamoto", "batterId": 672960, "pitchType": "Cutter", "call": "Called Strike", "outcome": "strike", "pX": 0.7535, "pZ": 2.1048, "szTop": 3.256, "szBottom": 1.643, "startSpeed": 91.8, "spinRate": 1945, "playId": "20682779-9144-320b-aa84-115bac322126", "inning": 7, "halfInning": "top", "atBatIndex": 47, "pitchInPa": 3, "paResult": "Groundout"}, {"pitcher": "Brandon Sproat", "pitcherId": 687075, "batter": "Kazuma Okamoto", "batterId": 672960, "pitchType": "Sinker", "call": "In play, out(s)", "outcome": "inplay", "pX": 0.2786, "pZ": 1.9975, "szTop": 3.256, "szBottom": 1.643, "startSpeed": 95.1, "spinRate": 1900, "playId": "bd2b5a8e-3194-373f-9d62-135f675c143c", "inning": 7, "halfInning": "top", "atBatIndex": 47, "pitchInPa": 4, "paResult": "Groundout", "launchSpeed": 105.9, "launchAngle": -23.0, "trajectory": "ground_ball"}, {"pitcher": "Aaron Ashby", "pitcherId": 676879, "batter": "Andr\u00e9s Gim\u00e9nez", "batterId": 665926, "pitchType": "Sinker", "call": "Foul Bunt", "outcome": "strike", "pX": 0.7138, "pZ": 1.8606, "szTop": 3.165, "szBottom": 1.597, "startSpeed": 96.7, "spinRate": 2084, "playId": "cf83059c-b0db-3064-97c7-9cbb1b157745", "inning": 7, "halfInning": "top", "atBatIndex": 48, "pitchInPa": 1, "paResult": "Single"}, {"pitcher": "Aaron Ashby", "pitcherId": 676879, "batter": "Andr\u00e9s Gim\u00e9nez", "batterId": 665926, "pitchType": "Sinker", "call": "Swinging Strike", "outcome": "strike", "pX": 0.5308, "pZ": 1.2861, "szTop": 3.165, "szBottom": 1.597, "startSpeed": 95.9, "spinRate": 2151, "playId": "8322382c-6fdd-344e-ab44-13c77f482c35", "inning": 7, "halfInning": "top", "atBatIndex": 48, "pitchInPa": 2, "paResult": "Single"}, {"pitcher": "Aaron Ashby", "pitcherId": 676879, "batter": "Andr\u00e9s Gim\u00e9nez", "batterId": 665926, "pitchType": "Slider", "call": "In play, no out", "outcome": "inplay", "pX": -0.8478, "pZ": 1.284, "szTop": 3.165, "szBottom": 1.597, "startSpeed": 83.4, "spinRate": 2383, "playId": "7b88c8b9-b242-3882-96e2-6c6263d6dbd5", "inning": 7, "halfInning": "top", "atBatIndex": 48, "pitchInPa": 3, "paResult": "Single", "launchSpeed": 58.3, "launchAngle": -47.0, "trajectory": "ground_ball"}, {"pitcher": "Aaron Ashby", "pitcherId": 676879, "batter": "Ernie Clement", "batterId": 676391, "pitchType": "Curveball", "call": "Ball", "outcome": "ball", "pX": 0.8942, "pZ": 3.0895, "szTop": 3.191, "szBottom": 1.61, "startSpeed": 79.8, "spinRate": 2672, "playId": "ebc08e17-5cef-3fbc-aaae-fdac4d9632fc", "inning": 7, "halfInning": "top", "atBatIndex": 49, "pitchInPa": 1, "paResult": "Groundout"}, {"pitcher": "Aaron Ashby", "pitcherId": 676879, "batter": "Ernie Clement", "batterId": 676391, "pitchType": "Sinker", "call": "Ball", "outcome": "ball", "pX": 0.8427, "pZ": 2.1795, "szTop": 3.191, "szBottom": 1.61, "startSpeed": 95.9, "spinRate": 2002, "playId": "cec27e25-4502-3698-a642-116e80fcaabb", "inning": 7, "halfInning": "top", "atBatIndex": 49, "pitchInPa": 2, "paResult": "Groundout"}, {"pitcher": "Aaron Ashby", "pitcherId": 676879, "batter": "Ernie Clement", "batterId": 676391, "pitchType": "Sinker", "call": "Called Strike", "outcome": "strike", "pX": 0.1584, "pZ": 2.2621, "szTop": 3.191, "szBottom": 1.61, "startSpeed": 96.2, "spinRate": 1998, "playId": "eb9ff6d4-07cb-3c9f-9f55-d276e4512777", "inning": 7, "halfInning": "top", "atBatIndex": 49, "pitchInPa": 3, "paResult": "Groundout"}, {"pitcher": "Aaron Ashby", "pitcherId": 676879, "batter": "Ernie Clement", "batterId": 676391, "pitchType": "Sinker", "call": "In play, out(s)", "outcome": "inplay", "pX": -0.0817, "pZ": 2.5147, "szTop": 3.191, "szBottom": 1.61, "startSpeed": 95.8, "spinRate": 1971, "playId": "19f74c35-ffed-367d-bc06-e4445dc46257", "inning": 7, "halfInning": "top", "atBatIndex": 49, "pitchInPa": 4, "paResult": "Groundout", "launchSpeed": 94.2, "launchAngle": -0.0, "trajectory": "ground_ball"}, {"pitcher": "Tommy Nance", "pitcherId": 667297, "batter": "Garrett Mitchell", "batterId": 669003, "pitchType": "Curveball", "call": "Ball", "outcome": "ball", "pX": 2.6644, "pZ": -0.6387, "szTop": 3.293, "szBottom": 1.662, "startSpeed": 83.8, "spinRate": 2922, "playId": "e984ed94-c3e9-3f05-a162-c27c45bb1463", "inning": 7, "halfInning": "bottom", "atBatIndex": 50, "pitchInPa": 1, "paResult": "Walk"}, {"pitcher": "Tommy Nance", "pitcherId": 667297, "batter": "Garrett Mitchell", "batterId": 669003, "pitchType": "Curveball", "call": "Called Strike", "outcome": "strike", "pX": 0.7618, "pZ": 2.3824, "szTop": 3.293, "szBottom": 1.662, "startSpeed": 82.3, "spinRate": 2715, "playId": "c5ccf333-8df1-3417-a8d5-c10cd64b72e8", "inning": 7, "halfInning": "bottom", "atBatIndex": 50, "pitchInPa": 2, "paResult": "Walk"}, {"pitcher": "Tommy Nance", "pitcherId": 667297, "batter": "Garrett Mitchell", "batterId": 669003, "pitchType": "Sinker", "call": "Foul", "outcome": "strike", "pX": 0.0009, "pZ": 2.8904, "szTop": 3.293, "szBottom": 1.662, "startSpeed": 93.1, "spinRate": 1970, "playId": "ef8a7fad-dd89-3630-8f6a-bf894fa254f6", "inning": 7, "halfInning": "bottom", "atBatIndex": 50, "pitchInPa": 3, "paResult": "Walk"}, {"pitcher": "Tommy Nance", "pitcherId": 667297, "batter": "Garrett Mitchell", "batterId": 669003, "pitchType": "Curveball", "call": "Ball", "outcome": "ball", "pX": 1.3873, "pZ": 2.5708, "szTop": 3.293, "szBottom": 1.662, "startSpeed": 85.6, "spinRate": 2828, "playId": "86678cbd-7b64-345b-a4ae-fa015d8675ef", "inning": 7, "halfInning": "bottom", "atBatIndex": 50, "pitchInPa": 4, "paResult": "Walk"}, {"pitcher": "Tommy Nance", "pitcherId": 667297, "batter": "Garrett Mitchell", "batterId": 669003, "pitchType": "Curveball", "call": "Ball", "outcome": "ball", "pX": 1.093, "pZ": 1.8674, "szTop": 3.293, "szBottom": 1.662, "startSpeed": 85.5, "spinRate": 2820, "playId": "0f3e7220-bb3f-38b8-a39f-d9b02f34dc93", "inning": 7, "halfInning": "bottom", "atBatIndex": 50, "pitchInPa": 5, "paResult": "Walk"}, {"pitcher": "Tommy Nance", "pitcherId": 667297, "batter": "Garrett Mitchell", "batterId": 669003, "pitchType": "Curveball", "call": "Ball", "outcome": "ball", "pX": 1.7916, "pZ": 1.2683, "szTop": 3.293, "szBottom": 1.662, "startSpeed": 85.4, "spinRate": 2957, "playId": "ef7c771b-6e1d-388e-b5a6-c5be16358336", "inning": 7, "halfInning": "bottom", "atBatIndex": 50, "pitchInPa": 6, "paResult": "Walk"}, {"pitcher": "Tommy Nance", "pitcherId": 667297, "batter": "Greg Jones", "batterId": 675659, "pitchType": "Sinker", "call": "In play, out(s)", "outcome": "inplay", "pX": -0.3587, "pZ": 2.9134, "szTop": 3.203, "szBottom": 1.617, "startSpeed": 94.8, "spinRate": 2338, "playId": "ac5b285e-bcce-3aa2-a5e4-1dd5fe5c87de", "inning": 7, "halfInning": "bottom", "atBatIndex": 51, "pitchInPa": 1, "paResult": "Sac Bunt", "launchSpeed": 19.0, "launchAngle": -61.0, "trajectory": "bunt_grounder"}, {"pitcher": "Joe Mantiply", "pitcherId": 573009, "batter": "David Hamilton", "batterId": 666152, "pitchType": "Sinker", "call": "In play, no out", "outcome": "inplay", "pX": 0.5811, "pZ": 2.4083, "szTop": 3.135, "szBottom": 1.582, "startSpeed": 87.6, "spinRate": 2161, "playId": "d30dc77a-a1fd-30e9-8d9e-d82533a106a8", "inning": 7, "halfInning": "bottom", "atBatIndex": 52, "pitchInPa": 1, "paResult": "Single", "launchSpeed": 36.1, "launchAngle": -53.0, "trajectory": "bunt_grounder"}, {"pitcher": "Joe Mantiply", "pitcherId": 573009, "batter": "Joey Ortiz", "batterId": 687401, "pitchType": "Curveball", "call": "Called Strike", "outcome": "strike", "pX": 0.8255, "pZ": 2.602, "szTop": 3.137, "szBottom": 1.583, "startSpeed": 79.3, "spinRate": 2159, "playId": "7b920bd0-af27-31b3-9059-b22b6796afe2", "inning": 7, "halfInning": "bottom", "atBatIndex": 53, "pitchInPa": 1, "paResult": "Sac Bunt"}, {"pitcher": "Joe Mantiply", "pitcherId": 573009, "batter": "Joey Ortiz", "batterId": 687401, "pitchType": "Changeup", "call": "Ball", "outcome": "ball", "pX": 1.7199, "pZ": 1.8207, "szTop": 3.137, "szBottom": 1.583, "startSpeed": 80.8, "spinRate": 1658, "playId": "216e2ef4-a35f-36bc-8072-32bbbbc76253", "inning": 7, "halfInning": "bottom", "atBatIndex": 53, "pitchInPa": 2, "paResult": "Sac Bunt"}, {"pitcher": "Joe Mantiply", "pitcherId": 573009, "batter": "Joey Ortiz", "batterId": 687401, "pitchType": "Changeup", "call": "In play, run(s)", "outcome": "inplay", "pX": 0.0954, "pZ": 1.3949, "szTop": 3.137, "szBottom": 1.583, "startSpeed": 79.8, "spinRate": 1700, "playId": "47917976-f1dc-3ab6-906b-96acdf7550fc", "inning": 7, "halfInning": "bottom", "atBatIndex": 53, "pitchInPa": 3, "paResult": "Sac Bunt", "launchSpeed": 22.7, "launchAngle": -74.0, "trajectory": "bunt_grounder"}, {"pitcher": "Joe Mantiply", "pitcherId": 573009, "batter": "Brandon Lockridge", "batterId": 663604, "pitchType": "Changeup", "call": "Swinging Strike", "outcome": "strike", "pX": 1.3391, "pZ": 2.2713, "szTop": 3.226, "szBottom": 1.628, "startSpeed": 80.3, "spinRate": 1607, "playId": "37fbf330-ca23-333a-9bc4-f01972cf37d0", "inning": 7, "halfInning": "bottom", "atBatIndex": 54, "pitchInPa": 1, "paResult": "Strikeout"}, {"pitcher": "Joe Mantiply", "pitcherId": 573009, "batter": "Brandon Lockridge", "batterId": 663604, "pitchType": "Changeup", "call": "Swinging Strike", "outcome": "strike", "pX": 0.8607, "pZ": 2.0053, "szTop": 3.226, "szBottom": 1.628, "startSpeed": 80.3, "spinRate": 1637, "playId": "9d4eae1a-a3e3-346e-8531-6f52c3411559", "inning": 7, "halfInning": "bottom", "atBatIndex": 54, "pitchInPa": 2, "paResult": "Strikeout"}, {"pitcher": "Joe Mantiply", "pitcherId": 573009, "batter": "Brandon Lockridge", "batterId": 663604, "pitchType": "Changeup", "call": "Foul Tip", "outcome": "strike", "pX": -0.0648, "pZ": 1.6351, "szTop": 3.226, "szBottom": 1.628, "startSpeed": 82.3, "spinRate": 1594, "playId": "29efe4c2-4aff-3a27-961a-6c454a5e4f28", "inning": 7, "halfInning": "bottom", "atBatIndex": 54, "pitchInPa": 3, "paResult": "Strikeout"}, {"pitcher": "Trevor Megill", "pitcherId": 656730, "batter": "Tyler Heineman", "batterId": 623168, "pitchType": "Four-Seam Fastball", "call": "Ball", "outcome": "ball", "pX": -0.1146, "pZ": 1.3958, "szTop": 3.11, "szBottom": 1.57, "startSpeed": 97.1, "spinRate": 2280, "playId": "97033625-c447-3f7a-a774-0804ef2908ed", "inning": 8, "halfInning": "top", "atBatIndex": 55, "pitchInPa": 1, "paResult": "Flyout"}, {"pitcher": "Trevor Megill", "pitcherId": 656730, "batter": "Tyler Heineman", "batterId": 623168, "pitchType": "Four-Seam Fastball", "call": "Called Strike", "outcome": "strike", "pX": -0.7166, "pZ": 1.841, "szTop": 3.11, "szBottom": 1.57, "startSpeed": 97.5, "spinRate": 2391, "playId": "879cd619-0d06-36c5-93c7-4fe725402c9b", "inning": 8, "halfInning": "top", "atBatIndex": 55, "pitchInPa": 2, "paResult": "Flyout"}, {"pitcher": "Trevor Megill", "pitcherId": 656730, "batter": "Tyler Heineman", "batterId": 623168, "pitchType": "Knuckle Curve", "call": "In play, out(s)", "outcome": "inplay", "pX": 0.1195, "pZ": 2.8095, "szTop": 3.11, "szBottom": 1.57, "startSpeed": 86.5, "spinRate": 2733, "playId": "8001f4a9-0344-3442-9473-cbcd6f6f0e55", "inning": 8, "halfInning": "top", "atBatIndex": 55, "pitchInPa": 3, "paResult": "Flyout", "launchSpeed": 75.4, "launchAngle": 49.0, "trajectory": "fly_ball"}, {"pitcher": "Trevor Megill", "pitcherId": 656730, "batter": "Davis Schneider", "batterId": 676914, "pitchType": "Knuckle Curve", "call": "Ball", "outcome": "ball", "pX": 1.1964, "pZ": 2.2717, "szTop": 3.045, "szBottom": 1.537, "startSpeed": 88.0, "spinRate": 2656, "playId": "6f995166-e795-33dc-9dde-f6ecad2eeaff", "inning": 8, "halfInning": "top", "atBatIndex": 56, "pitchInPa": 1, "paResult": "Strikeout"}, {"pitcher": "Trevor Megill", "pitcherId": 656730, "batter": "Davis Schneider", "batterId": 676914, "pitchType": "Knuckle Curve", "call": "Called Strike", "outcome": "strike", "pX": 0.3119, "pZ": 3.1298, "szTop": 3.045, "szBottom": 1.537, "startSpeed": 87.6, "spinRate": 2612, "playId": "17ccaf40-f2b0-35e8-85f8-1880fdd51463", "inning": 8, "halfInning": "top", "atBatIndex": 56, "pitchInPa": 2, "paResult": "Strikeout"}, {"pitcher": "Trevor Megill", "pitcherId": 656730, "batter": "Davis Schneider", "batterId": 676914, "pitchType": "Knuckle Curve", "call": "Foul", "outcome": "strike", "pX": -0.4936, "pZ": 1.5101, "szTop": 3.045, "szBottom": 1.537, "startSpeed": 88.1, "spinRate": 2675, "playId": "d6dd6d2b-4920-3677-afeb-5995d8f7ec41", "inning": 8, "halfInning": "top", "atBatIndex": 56, "pitchInPa": 3, "paResult": "Strikeout"}, {"pitcher": "Trevor Megill", "pitcherId": 656730, "batter": "Davis Schneider", "batterId": 676914, "pitchType": "Four-Seam Fastball", "call": "Ball", "outcome": "ball", "pX": -0.8772, "pZ": 2.469, "szTop": 3.045, "szBottom": 1.537, "startSpeed": 98.2, "spinRate": 2414, "playId": "3515045c-3b4a-3560-90ee-282f59e2ac89", "inning": 8, "halfInning": "top", "atBatIndex": 56, "pitchInPa": 4, "paResult": "Strikeout"}, {"pitcher": "Trevor Megill", "pitcherId": 656730, "batter": "Davis Schneider", "batterId": 676914, "pitchType": "Four-Seam Fastball", "call": "Foul", "outcome": "strike", "pX": 0.3263, "pZ": 2.6516, "szTop": 3.045, "szBottom": 1.537, "startSpeed": 97.1, "spinRate": 2363, "playId": "88db69b2-7451-342b-8b11-4de3c2f13a1c", "inning": 8, "halfInning": "top", "atBatIndex": 56, "pitchInPa": 5, "paResult": "Strikeout"}, {"pitcher": "Trevor Megill", "pitcherId": 656730, "batter": "Davis Schneider", "batterId": 676914, "pitchType": "Four-Seam Fastball", "call": "Foul", "outcome": "strike", "pX": -0.4307, "pZ": 2.4893, "szTop": 3.045, "szBottom": 1.537, "startSpeed": 97.6, "spinRate": 2216, "playId": "595bd1e1-abf2-3764-a01d-384f18cf9c01", "inning": 8, "halfInning": "top", "atBatIndex": 56, "pitchInPa": 6, "paResult": "Strikeout"}, {"pitcher": "Trevor Megill", "pitcherId": 656730, "batter": "Davis Schneider", "batterId": 676914, "pitchType": "Knuckle Curve", "call": "Foul", "outcome": "strike", "pX": -0.1341, "pZ": 0.9096, "szTop": 3.045, "szBottom": 1.537, "startSpeed": 88.8, "spinRate": 2528, "playId": "4b907790-6c1b-35ec-b31a-ff3c040bb409", "inning": 8, "halfInning": "top", "atBatIndex": 56, "pitchInPa": 7, "paResult": "Strikeout"}, {"pitcher": "Trevor Megill", "pitcherId": 656730, "batter": "Davis Schneider", "batterId": 676914, "pitchType": "Knuckle Curve", "call": "Ball", "outcome": "ball", "pX": 0.5911, "pZ": -0.3017, "szTop": 3.045, "szBottom": 1.537, "startSpeed": 88.4, "spinRate": 2549, "playId": "14fb6eea-29c4-388b-94a0-8b9c4b11a038", "inning": 8, "halfInning": "top", "atBatIndex": 56, "pitchInPa": 8, "paResult": "Strikeout"}, {"pitcher": "Trevor Megill", "pitcherId": 656730, "batter": "Davis Schneider", "batterId": 676914, "pitchType": "Four-Seam Fastball", "call": "Swinging Strike", "outcome": "strike", "pX": 0.6513, "pZ": 1.4331, "szTop": 3.045, "szBottom": 1.537, "startSpeed": 97.7, "spinRate": 2448, "playId": "0903bdf7-b14e-30a3-a0c2-4410d017ea39", "inning": 8, "halfInning": "top", "atBatIndex": 56, "pitchInPa": 9, "paResult": "Strikeout"}, {"pitcher": "Trevor Megill", "pitcherId": 656730, "batter": "Daulton Varsho", "batterId": 662139, "pitchType": "Four-Seam Fastball", "call": "Foul", "outcome": "strike", "pX": 0.2714, "pZ": 2.254, "szTop": 3.037, "szBottom": 1.532, "startSpeed": 97.8, "spinRate": 2378, "playId": "a1cdb723-26fa-3efc-ad3a-173959e753f2", "inning": 8, "halfInning": "top", "atBatIndex": 57, "pitchInPa": 1, "paResult": "Strikeout"}, {"pitcher": "Trevor Megill", "pitcherId": 656730, "batter": "Daulton Varsho", "batterId": 662139, "pitchType": "Knuckle Curve", "call": "Ball", "outcome": "ball", "pX": 0.5465, "pZ": 0.1919, "szTop": 3.037, "szBottom": 1.532, "startSpeed": 87.4, "spinRate": 2727, "playId": "77cfed58-0c25-3d9f-8e39-6a256041a032", "inning": 8, "halfInning": "top", "atBatIndex": 57, "pitchInPa": 2, "paResult": "Strikeout"}, {"pitcher": "Trevor Megill", "pitcherId": 656730, "batter": "Daulton Varsho", "batterId": 662139, "pitchType": "Knuckle Curve", "call": "Swinging Strike", "outcome": "strike", "pX": -0.0353, "pZ": 2.0453, "szTop": 3.037, "szBottom": 1.532, "startSpeed": 87.8, "spinRate": 2607, "playId": "4c7a31b9-102f-3c0b-858c-826e64829084", "inning": 8, "halfInning": "top", "atBatIndex": 57, "pitchInPa": 3, "paResult": "Strikeout"}, {"pitcher": "Trevor Megill", "pitcherId": 656730, "batter": "Daulton Varsho", "batterId": 662139, "pitchType": "Knuckle Curve", "call": "Swinging Strike", "outcome": "strike", "pX": 1.1107, "pZ": 1.2019, "szTop": 3.037, "szBottom": 1.532, "startSpeed": 87.3, "spinRate": 2696, "playId": "d38d5040-7d82-3e23-85fc-c148790699ab", "inning": 8, "halfInning": "top", "atBatIndex": 57, "pitchInPa": 4, "paResult": "Strikeout"}, {"pitcher": "Joe Mantiply", "pitcherId": 573009, "batter": "Brice Turang", "batterId": 668930, "pitchType": "Curveball", "call": "Called Strike", "outcome": "strike", "pX": 0.6469, "pZ": 2.8274, "szTop": 3.21, "szBottom": 1.62, "startSpeed": 80.7, "spinRate": 2303, "playId": "8d538790-b7fe-31f0-aa09-75cf39a60f3c", "inning": 8, "halfInning": "bottom", "atBatIndex": 58, "pitchInPa": 1, "paResult": "Groundout"}, {"pitcher": "Joe Mantiply", "pitcherId": 573009, "batter": "Brice Turang", "batterId": 668930, "pitchType": "Sinker", "call": "Called Strike", "outcome": "strike", "pX": -0.1145, "pZ": 2.5768, "szTop": 3.21, "szBottom": 1.62, "startSpeed": 89.0, "spinRate": 2198, "playId": "451f5e3d-0f0b-3843-83f6-3789fba38f04", "inning": 8, "halfInning": "bottom", "atBatIndex": 58, "pitchInPa": 2, "paResult": "Groundout"}, {"pitcher": "Joe Mantiply", "pitcherId": 573009, "batter": "Brice Turang", "batterId": 668930, "pitchType": "Sinker", "call": "In play, out(s)", "outcome": "inplay", "pX": -0.0783, "pZ": 2.4595, "szTop": 3.21, "szBottom": 1.62, "startSpeed": 89.1, "spinRate": 2200, "playId": "0b974b50-7cee-37bc-aee8-e0be704e99f5", "inning": 8, "halfInning": "bottom", "atBatIndex": 58, "pitchInPa": 3, "paResult": "Groundout", "launchSpeed": 99.5, "launchAngle": -20.0, "trajectory": "ground_ball"}, {"pitcher": "Louis Varland", "pitcherId": 686973, "batter": "William Contreras", "batterId": 661388, "pitchType": "Slider", "call": "Called Strike", "outcome": "strike", "pX": 0.5199, "pZ": 2.9718, "szTop": 3.133, "szBottom": 1.581, "startSpeed": 90.7, "spinRate": 2303, "playId": "9d8edc19-d8dd-36bf-ab7a-a0e418da5320", "inning": 8, "halfInning": "bottom", "atBatIndex": 59, "pitchInPa": 1, "paResult": "Flyout"}, {"pitcher": "Louis Varland", "pitcherId": 686973, "batter": "William Contreras", "batterId": 661388, "pitchType": "Knuckle Curve", "call": "Ball", "outcome": "ball", "pX": 2.0669, "pZ": 0.27, "szTop": 3.133, "szBottom": 1.581, "startSpeed": 86.9, "spinRate": 2266, "playId": "b2843e5c-83ec-370c-a47d-448a1a31d997", "inning": 8, "halfInning": "bottom", "atBatIndex": 59, "pitchInPa": 2, "paResult": "Flyout"}, {"pitcher": "Louis Varland", "pitcherId": 686973, "batter": "William Contreras", "batterId": 661388, "pitchType": "Knuckle Curve", "call": "Ball", "outcome": "ball", "pX": 0.8433, "pZ": 1.3769, "szTop": 3.133, "szBottom": 1.581, "startSpeed": 85.4, "spinRate": 2361, "playId": "f590241e-ebfb-3a17-901e-e4dbbbed370d", "inning": 8, "halfInning": "bottom", "atBatIndex": 59, "pitchInPa": 3, "paResult": "Flyout"}, {"pitcher": "Louis Varland", "pitcherId": 686973, "batter": "William Contreras", "batterId": 661388, "pitchType": "Slider", "call": "In play, out(s)", "outcome": "inplay", "pX": 0.2769, "pZ": 2.1909, "szTop": 3.133, "szBottom": 1.581, "startSpeed": 90.5, "spinRate": 2481, "playId": "55f1c1f2-dd79-392a-a294-767cca1b006f", "inning": 8, "halfInning": "bottom", "atBatIndex": 59, "pitchInPa": 4, "paResult": "Flyout", "launchSpeed": 90.6, "launchAngle": 58.0, "trajectory": "fly_ball"}, {"pitcher": "Louis Varland", "pitcherId": 686973, "batter": "Gary S\u00e1nchez", "batterId": 596142, "pitchType": "Slider", "call": "Foul", "outcome": "strike", "pX": 0.6077, "pZ": 2.7652, "szTop": 3.311, "szBottom": 1.671, "startSpeed": 91.8, "spinRate": 2459, "playId": "12063c7d-409f-3ed6-afaa-93f4ee29ca60", "inning": 8, "halfInning": "bottom", "atBatIndex": 60, "pitchInPa": 1, "paResult": "Double"}, {"pitcher": "Louis Varland", "pitcherId": 686973, "batter": "Gary S\u00e1nchez", "batterId": 596142, "pitchType": "Sinker", "call": "Ball", "outcome": "ball", "pX": 0.8413, "pZ": 0.6717, "szTop": 3.311, "szBottom": 1.671, "startSpeed": 94.7, "spinRate": 1993, "playId": "77dabcbe-808d-33be-bae2-27a4d760fdf7", "inning": 8, "halfInning": "bottom", "atBatIndex": 60, "pitchInPa": 2, "paResult": "Double"}, {"pitcher": "Louis Varland", "pitcherId": 686973, "batter": "Gary S\u00e1nchez", "batterId": 596142, "pitchType": "Four-Seam Fastball", "call": "Ball", "outcome": "ball", "pX": 0.7797, "pZ": 1.3297, "szTop": 3.311, "szBottom": 1.671, "startSpeed": 98.1, "spinRate": 2287, "playId": "f7c691ca-01d7-341c-ae97-c1a387e14e5e", "inning": 8, "halfInning": "bottom", "atBatIndex": 60, "pitchInPa": 3, "paResult": "Double"}, {"pitcher": "Louis Varland", "pitcherId": 686973, "batter": "Gary S\u00e1nchez", "batterId": 596142, "pitchType": "Four-Seam Fastball", "call": "Ball", "outcome": "ball", "pX": 1.8979, "pZ": 1.6591, "szTop": 3.311, "szBottom": 1.671, "startSpeed": 97.6, "spinRate": 2285, "playId": "d64567b8-c888-3760-b2b5-38e40bd5cde4", "inning": 8, "halfInning": "bottom", "atBatIndex": 60, "pitchInPa": 4, "paResult": "Double"}, {"pitcher": "Louis Varland", "pitcherId": 686973, "batter": "Gary S\u00e1nchez", "batterId": 596142, "pitchType": "Four-Seam Fastball", "call": "Foul", "outcome": "strike", "pX": 0.1978, "pZ": 2.2313, "szTop": 3.311, "szBottom": 1.671, "startSpeed": 97.5, "spinRate": 2285, "playId": "fcbad75f-1342-39fa-b7f2-3b9e49684844", "inning": 8, "halfInning": "bottom", "atBatIndex": 60, "pitchInPa": 5, "paResult": "Double"}, {"pitcher": "Louis Varland", "pitcherId": 686973, "batter": "Gary S\u00e1nchez", "batterId": 596142, "pitchType": "Four-Seam Fastball", "call": "In play, no out", "outcome": "inplay", "pX": 0.1413, "pZ": 2.3577, "szTop": 3.311, "szBottom": 1.671, "startSpeed": 98.2, "spinRate": 2175, "playId": "7a3c6ae2-026e-3394-a872-6a25fa51d3ec", "inning": 8, "halfInning": "bottom", "atBatIndex": 60, "pitchInPa": 6, "paResult": "Double", "launchSpeed": 89.3, "launchAngle": 14.0, "trajectory": "line_drive"}, {"pitcher": "Louis Varland", "pitcherId": 686973, "batter": "Jake Bauers", "batterId": 641343, "pitchType": "Four-Seam Fastball", "call": "Called Strike", "outcome": "strike", "pX": -0.0619, "pZ": 2.1021, "szTop": 3.217, "szBottom": 1.624, "startSpeed": 98.2, "spinRate": 2377, "playId": "3fe28722-7c33-3844-bf60-5ce5df232187", "inning": 8, "halfInning": "bottom", "atBatIndex": 61, "pitchInPa": 1, "paResult": "Strikeout"}, {"pitcher": "Louis Varland", "pitcherId": 686973, "batter": "Jake Bauers", "batterId": 641343, "pitchType": "Changeup", "call": "Called Strike", "outcome": "strike", "pX": 0.5073, "pZ": 1.8371, "szTop": 3.217, "szBottom": 1.624, "startSpeed": 93.6, "spinRate": 1469, "playId": "7a82f93b-7802-3c1f-869a-c5547f4c34e7", "inning": 8, "halfInning": "bottom", "atBatIndex": 61, "pitchInPa": 2, "paResult": "Strikeout"}, {"pitcher": "Louis Varland", "pitcherId": 686973, "batter": "Jake Bauers", "batterId": 641343, "pitchType": "Four-Seam Fastball", "call": "Called Strike", "outcome": "strike", "pX": 0.0753, "pZ": 2.5366, "szTop": 3.217, "szBottom": 1.624, "startSpeed": 99.0, "spinRate": 2311, "playId": "d55430d2-931a-33f0-a28b-10836296aa5e", "inning": 8, "halfInning": "bottom", "atBatIndex": 61, "pitchInPa": 3, "paResult": "Strikeout"}, {"pitcher": "Angel Zerpa", "pitcherId": 672582, "batter": "Vladimir Guerrero Jr.", "batterId": 665489, "pitchType": "Sinker", "call": "Ball", "outcome": "ball", "pX": -0.0714, "pZ": 1.5067, "szTop": 3.209, "szBottom": 1.619, "startSpeed": 94.8, "spinRate": 2006, "playId": "fd4c3b21-883d-3a56-bf83-5c30d2b80f3c", "inning": 9, "halfInning": "top", "atBatIndex": 62, "pitchInPa": 1, "paResult": "Single"}, {"pitcher": "Angel Zerpa", "pitcherId": 672582, "batter": "Vladimir Guerrero Jr.", "batterId": 665489, "pitchType": "Sinker", "call": "In play, no out", "outcome": "inplay", "pX": -0.0269, "pZ": 1.9767, "szTop": 3.209, "szBottom": 1.619, "startSpeed": 94.9, "spinRate": 1891, "playId": "6ec51277-22d2-304a-95bf-e8d696d331e8", "inning": 9, "halfInning": "top", "atBatIndex": 62, "pitchInPa": 2, "paResult": "Single", "launchSpeed": 114.6, "launchAngle": -6.0, "trajectory": "ground_ball"}, {"pitcher": "Angel Zerpa", "pitcherId": 672582, "batter": "Eloy Jim\u00e9nez", "batterId": 650391, "pitchType": "Sinker", "call": "Called Strike", "outcome": "strike", "pX": 0.6937, "pZ": 2.3508, "szTop": 3.373, "szBottom": 1.702, "startSpeed": 94.5, "spinRate": 1966, "playId": "c85ee288-23b0-3df9-aeb3-39cd3d107b51", "inning": 9, "halfInning": "top", "atBatIndex": 63, "pitchInPa": 1, "paResult": "Groundout"}, {"pitcher": "Angel Zerpa", "pitcherId": 672582, "batter": "Eloy Jim\u00e9nez", "batterId": 650391, "pitchType": "Slider", "call": "Ball In Dirt", "outcome": "ball", "pX": -1.5906, "pZ": 1.0027, "szTop": 3.373, "szBottom": 1.702, "startSpeed": 88.3, "spinRate": 2454, "playId": "a01ff7d3-ea9c-32a5-99cd-ab0d60f44042", "inning": 9, "halfInning": "top", "atBatIndex": 63, "pitchInPa": 2, "paResult": "Groundout"}, {"pitcher": "Angel Zerpa", "pitcherId": 672582, "batter": "Eloy Jim\u00e9nez", "batterId": 650391, "pitchType": "Slider", "call": "Ball", "outcome": "ball", "pX": 0.921, "pZ": 3.0505, "szTop": 3.373, "szBottom": 1.702, "startSpeed": 85.6, "spinRate": 2441, "playId": "88e172ef-7c2c-33f8-b6c7-f52a4b13529d", "inning": 9, "halfInning": "top", "atBatIndex": 63, "pitchInPa": 3, "paResult": "Groundout"}, {"pitcher": "Angel Zerpa", "pitcherId": 672582, "batter": "Eloy Jim\u00e9nez", "batterId": 650391, "pitchType": "Sinker", "call": "In play, out(s)", "outcome": "inplay", "pX": 0.5143, "pZ": 2.8465, "szTop": 3.373, "szBottom": 1.702, "startSpeed": 95.1, "spinRate": 1986, "playId": "305ce6d7-af2c-375d-9902-fb20cef541a4", "inning": 9, "halfInning": "top", "atBatIndex": 63, "pitchInPa": 4, "paResult": "Groundout", "launchSpeed": 69.5, "launchAngle": -69.0, "trajectory": "ground_ball"}, {"pitcher": "Angel Zerpa", "pitcherId": 672582, "batter": "Lenyn Sosa", "batterId": 672820, "pitchType": "Sinker", "call": "In play, out(s)", "outcome": "inplay", "pX": -0.2575, "pZ": 2.3008, "szTop": 3.153, "szBottom": 1.591, "startSpeed": 95.5, "spinRate": 1926, "playId": "701fde24-eda9-31a5-80c1-e660997124cb", "inning": 9, "halfInning": "top", "atBatIndex": 64, "pitchInPa": 1, "paResult": "Groundout", "launchSpeed": 101.5, "launchAngle": 2.0, "trajectory": "ground_ball"}, {"pitcher": "Angel Zerpa", "pitcherId": 672582, "batter": "Kazuma Okamoto", "batterId": 672960, "pitchType": "Sinker", "call": "Ball", "outcome": "ball", "pX": 0.8024, "pZ": 4.1744, "szTop": 3.256, "szBottom": 1.643, "startSpeed": 95.5, "spinRate": 2044, "playId": "c752760d-3adb-3730-8a9c-dbbaba7ba96e", "inning": 9, "halfInning": "top", "atBatIndex": 65, "pitchInPa": 1, "paResult": "Groundout"}, {"pitcher": "Angel Zerpa", "pitcherId": 672582, "batter": "Kazuma Okamoto", "batterId": 672960, "pitchType": "Sinker", "call": "Called Strike", "outcome": "strike", "pX": -0.5502, "pZ": 2.4293, "szTop": 3.256, "szBottom": 1.643, "startSpeed": 95.3, "spinRate": 1887, "playId": "6c889664-1a59-3c39-9230-08abf9ce72f2", "inning": 9, "halfInning": "top", "atBatIndex": 65, "pitchInPa": 2, "paResult": "Groundout"}, {"pitcher": "Angel Zerpa", "pitcherId": 672582, "batter": "Kazuma Okamoto", "batterId": 672960, "pitchType": "Sinker", "call": "In play, out(s)", "outcome": "inplay", "pX": -0.2836, "pZ": 1.994, "szTop": 3.256, "szBottom": 1.643, "startSpeed": 95.3, "spinRate": 1836, "playId": "c6092941-3fe3-36ff-93e7-90561b441435", "inning": 9, "halfInning": "top", "atBatIndex": 65, "pitchInPa": 3, "paResult": "Groundout", "launchSpeed": 104.1, "launchAngle": -9.0, "trajectory": "ground_ball"}]}